{
  "https://pharma-shop.tn/-2" : {
    "transaction" : "https://pharma-shop.tn/-2",
    "sampleCount" : 2,
    "errorCount" : 0,
    "errorPct" : 0.0,
    "meanResTime" : 1046.0,
    "medianResTime" : 1046.0,
    "minResTime" : 38.0,
    "maxResTime" : 2054.0,
    "pct1ResTime" : 2054.0,
    "pct2ResTime" : 2054.0,
    "pct3ResTime" : 2054.0,
    "throughput" : 0.24369440721335445,
    "receivedKBytesPerSec" : 94.31021155720725,
    "sentKBytesPerSec" : 0.2664217664798343
  },
  "https://pharma-shop.tn/-1" : {
    "transaction" : "https://pharma-shop.tn/-1",
    "sampleCount" : 3,
    "errorCount" : 0,
    "errorPct" : 0.0,
    "meanResTime" : 256.6666666666667,
    "medianResTime" : 162.0,
    "minResTime" : 43.0,
    "maxResTime" : 565.0,
    "pct1ResTime" : 565.0,
    "pct2ResTime" : 565.0,
    "pct3ResTime" : 565.0,
    "throughput" : 0.3653190452995616,
    "receivedKBytesPerSec" : 2.0760872047004386,
    "sentKBytesPerSec" : 0.26055144148806625
  },
  "https://pharma-shop.tn/-0" : {
    "transaction" : "https://pharma-shop.tn/-0",
    "sampleCount" : 3,
    "errorCount" : 0,
    "errorPct" : 0.0,
    "meanResTime" : 567.6666666666666,
    "medianResTime" : 616.0,
    "minResTime" : 452.0,
    "maxResTime" : 635.0,
    "pct1ResTime" : 635.0,
    "pct2ResTime" : 635.0,
    "pct3ResTime" : 635.0,
    "throughput" : 0.3472222222222222,
    "receivedKBytesPerSec" : 174.25243236400462,
    "sentKBytesPerSec" : 0.23261176215277776
  },
  "https://pharma-shop.tn/-6" : {
    "transaction" : "https://pharma-shop.tn/-6",
    "sampleCount" : 2,
    "errorCount" : 0,
    "errorPct" : 0.0,
    "meanResTime" : 111.0,
    "medianResTime" : 111.0,
    "minResTime" : 46.0,
    "maxResTime" : 176.0,
    "pct1ResTime" : 176.0,
    "pct2ResTime" : 176.0,
    "pct3ResTime" : 176.0,
    "throughput" : 0.24348672997321646,
    "receivedKBytesPerSec" : 1.7230728405770634,
    "sentKBytesPerSec" : 0.18998622778183588
  },
  "https://pharma-shop.tn/-90" : {
    "transaction" : "https://pharma-shop.tn/-90",
    "sampleCount" : 2,
    "errorCount" : 0,
    "errorPct" : 0.0,
    "meanResTime" : 50.5,
    "medianResTime" : 50.5,
    "minResTime" : 36.0,
    "maxResTime" : 65.0,
    "pct1ResTime" : 65.0,
    "pct2ResTime" : 65.0,
    "pct3ResTime" : 65.0,
    "throughput" : 0.3099333643266698,
    "receivedKBytesPerSec" : 1.4670381024329768,
    "sentKBytesPerSec" : 0.25333420502092047
  },
  "https://pharma-shop.tn/-5" : {
    "transaction" : "https://pharma-shop.tn/-5",
    "sampleCount" : 2,
    "errorCount" : 0,
    "errorPct" : 0.0,
    "meanResTime" : 42.5,
    "medianResTime" : 42.5,
    "minResTime" : 42.0,
    "maxResTime" : 43.0,
    "pct1ResTime" : 43.0,
    "pct2ResTime" : 43.0,
    "pct3ResTime" : 43.0,
    "throughput" : 0.24357569114602362,
    "receivedKBytesPerSec" : 1.3431153711484594,
    "sentKBytesPerSec" : 0.18886630739252222
  },
  "https://pharma-shop.tn/-91" : {
    "transaction" : "https://pharma-shop.tn/-91",
    "sampleCount" : 2,
    "errorCount" : 0,
    "errorPct" : 0.0,
    "meanResTime" : 40.5,
    "medianResTime" : 40.5,
    "minResTime" : 35.0,
    "maxResTime" : 46.0,
    "pct1ResTime" : 46.0,
    "pct2ResTime" : 46.0,
    "pct3ResTime" : 46.0,
    "throughput" : 0.310896937665164,
    "receivedKBytesPerSec" : 1.7644312043370123,
    "sentKBytesPerSec" : 0.2544254235970776
  },
  "https://pharma-shop.tn/-4" : {
    "transaction" : "https://pharma-shop.tn/-4",
    "sampleCount" : 2,
    "errorCount" : 0,
    "errorPct" : 0.0,
    "meanResTime" : 114.5,
    "medianResTime" : 114.5,
    "minResTime" : 41.0,
    "maxResTime" : 188.0,
    "pct1ResTime" : 188.0,
    "pct2ResTime" : 188.0,
    "pct3ResTime" : 188.0,
    "throughput" : 0.243605359317905,
    "receivedKBytesPerSec" : 0.5477552146772229,
    "sentKBytesPerSec" : 0.18984089524969547
  },
  "https://pharma-shop.tn/-3" : {
    "transaction" : "https://pharma-shop.tn/-3",
    "sampleCount" : 2,
    "errorCount" : 0,
    "errorPct" : 0.0,
    "meanResTime" : 81.5,
    "medianResTime" : 81.5,
    "minResTime" : 22.0,
    "maxResTime" : 141.0,
    "pct1ResTime" : 141.0,
    "pct2ResTime" : 141.0,
    "pct3ResTime" : 141.0,
    "throughput" : 0.24417043096081065,
    "receivedKBytesPerSec" : 1.2536387116957635,
    "sentKBytesPerSec" : 0.14902980405322913
  },
  "https://pharma-shop.tn/-94" : {
    "transaction" : "https://pharma-shop.tn/-94",
    "sampleCount" : 2,
    "errorCount" : 0,
    "errorPct" : 0.0,
    "meanResTime" : 39.5,
    "medianResTime" : 39.5,
    "minResTime" : 38.0,
    "maxResTime" : 41.0,
    "pct1ResTime" : 41.0,
    "pct2ResTime" : 41.0,
    "pct3ResTime" : 41.0,
    "throughput" : 0.3110419906687403,
    "receivedKBytesPerSec" : 0.47810555987558323,
    "sentKBytesPerSec" : 0.25910040824261277
  },
  "https://pharma-shop.tn/-9" : {
    "transaction" : "https://pharma-shop.tn/-9",
    "sampleCount" : 2,
    "errorCount" : 0,
    "errorPct" : 0.0,
    "meanResTime" : 181.5,
    "medianResTime" : 181.5,
    "minResTime" : 37.0,
    "maxResTime" : 326.0,
    "pct1ResTime" : 326.0,
    "pct2ResTime" : 326.0,
    "pct3ResTime" : 326.0,
    "throughput" : 0.24676125848241826,
    "receivedKBytesPerSec" : 3.938661512954966,
    "sentKBytesPerSec" : 0.19663787785317705
  },
  "https://pharma-shop.tn/-95" : {
    "transaction" : "https://pharma-shop.tn/-95",
    "sampleCount" : 2,
    "errorCount" : 0,
    "errorPct" : 0.0,
    "meanResTime" : 34.0,
    "medianResTime" : 34.0,
    "minResTime" : 34.0,
    "maxResTime" : 34.0,
    "pct1ResTime" : 34.0,
    "pct2ResTime" : 34.0,
    "pct3ResTime" : 34.0,
    "throughput" : 0.31109037175299425,
    "receivedKBytesPerSec" : 0.6735228068128791,
    "sentKBytesPerSec" : 0.2676470874163944
  },
  "https://pharma-shop.tn/-8" : {
    "transaction" : "https://pharma-shop.tn/-8",
    "sampleCount" : 2,
    "errorCount" : 0,
    "errorPct" : 0.0,
    "meanResTime" : 49.0,
    "medianResTime" : 49.0,
    "minResTime" : 36.0,
    "maxResTime" : 62.0,
    "pct1ResTime" : 62.0,
    "pct2ResTime" : 62.0,
    "pct3ResTime" : 62.0,
    "throughput" : 0.24542888697999754,
    "receivedKBytesPerSec" : 2.7877989247146893,
    "sentKBytesPerSec" : 0.1915016413056817
  },
  "https://pharma-shop.tn/-92" : {
    "transaction" : "https://pharma-shop.tn/-92",
    "sampleCount" : 2,
    "errorCount" : 0,
    "errorPct" : 0.0,
    "meanResTime" : 39.0,
    "medianResTime" : 39.0,
    "minResTime" : 34.0,
    "maxResTime" : 44.0,
    "pct1ResTime" : 44.0,
    "pct2ResTime" : 44.0,
    "pct3ResTime" : 44.0,
    "throughput" : 0.3109936246306951,
    "receivedKBytesPerSec" : 1.118848157362774,
    "sentKBytesPerSec" : 0.25146750116622607
  },
  "https://pharma-shop.tn/-7" : {
    "transaction" : "https://pharma-shop.tn/-7",
    "sampleCount" : 2,
    "errorCount" : 0,
    "errorPct" : 0.0,
    "meanResTime" : 51.0,
    "medianResTime" : 51.0,
    "minResTime" : 51.0,
    "maxResTime" : 51.0,
    "pct1ResTime" : 51.0,
    "pct2ResTime" : 51.0,
    "pct3ResTime" : 51.0,
    "throughput" : 0.2439619419370578,
    "receivedKBytesPerSec" : 0.917001479019273,
    "sentKBytesPerSec" : 0.19130999939009513
  },
  "https://pharma-shop.tn/-93" : {
    "transaction" : "https://pharma-shop.tn/-93",
    "sampleCount" : 2,
    "errorCount" : 0,
    "errorPct" : 0.0,
    "meanResTime" : 40.5,
    "medianResTime" : 40.5,
    "minResTime" : 35.0,
    "maxResTime" : 46.0,
    "pct1ResTime" : 46.0,
    "pct2ResTime" : 46.0,
    "pct3ResTime" : 46.0,
    "throughput" : 0.3104144032283098,
    "receivedKBytesPerSec" : 2.203669437761912,
    "sentKBytesPerSec" : 0.2546368151482229
  },
  "https://pharma-shop.tn/-10" : {
    "transaction" : "https://pharma-shop.tn/-10",
    "sampleCount" : 2,
    "errorCount" : 0,
    "errorPct" : 0.0,
    "meanResTime" : 58.5,
    "medianResTime" : 58.5,
    "minResTime" : 35.0,
    "maxResTime" : 82.0,
    "pct1ResTime" : 82.0,
    "pct2ResTime" : 82.0,
    "pct3ResTime" : 82.0,
    "throughput" : 0.24724935097045372,
    "receivedKBytesPerSec" : 14.879388675979724,
    "sentKBytesPerSec" : 0.1953366454444307
  },
  "https://pharma-shop.tn/-98" : {
    "transaction" : "https://pharma-shop.tn/-98",
    "sampleCount" : 2,
    "errorCount" : 0,
    "errorPct" : 0.0,
    "meanResTime" : 38.0,
    "medianResTime" : 38.0,
    "minResTime" : 36.0,
    "maxResTime" : 40.0,
    "pct1ResTime" : 40.0,
    "pct2ResTime" : 40.0,
    "pct3ResTime" : 40.0,
    "throughput" : 0.31133250311332505,
    "receivedKBytesPerSec" : 0.5819242294520548,
    "sentKBytesPerSec" : 0.26025451432129515
  },
  "https://www.google.com/search?q=pharmashop&rlz=1C1PNJJ_frTN1050TN1050&sxsrf=APwXEdcSiZBW1PpYTEzwUR_yEox7_u6fbg%3A1680254294624&ei=VqUmZILfJemrkdUP7PyLkAk&oq=pha&gs_lcp=Cgxnd3Mtd2l6LXNlcnAQAxgAMgQIIxAnMgoIABCKBRCxAxBDMg0IABCKBRCxAxDJAxBDMggIABCABBCSAzIICAAQgAQQkgMyBwgAEIoFEEMyBwgAEIoFEEMyBwgAEIoFEEMyBwgAEIoFEEMyBwguEIoFEEM6BwgjEOoCECc6DQguEMcBENEDEOoCECc6DwgAEIoFEOoCELQCEEMYAToPCC4QigUQ6gIQtAIQQxgBOgsIABCABBCxAxCDAToICC4QgAQQsQM6CwgAEIoFELEDEIMBSgQIQRgAUABY8N0CYMzpAmgCcAF4AIABYIgBhQKSAQEzmAEAoAEBsAEUwAEB2gEGCAEQARgB&sclient=gws-wiz-serp" : {
    "transaction" : "https://www.google.com/search?q=pharmashop&rlz=1C1PNJJ_frTN1050TN1050&sxsrf=APwXEdcSiZBW1PpYTEzwUR_yEox7_u6fbg%3A1680254294624&ei=VqUmZILfJemrkdUP7PyLkAk&oq=pha&gs_lcp=Cgxnd3Mtd2l6LXNlcnAQAxgAMgQIIxAnMgoIABCKBRCxAxBDMg0IABCKBRCxAxDJAxBDMggIABCABBCSAzIICAAQgAQQkgMyBwgAEIoFEEMyBwgAEIoFEEMyBwgAEIoFEEMyBwgAEIoFEEMyBwguEIoFEEM6BwgjEOoCECc6DQguEMcBENEDEOoCECc6DwgAEIoFEOoCELQCEEMYAToPCC4QigUQ6gIQtAIQQxgBOgsIABCABBCxAxCDAToICC4QgAQQsQM6CwgAEIoFELEDEIMBSgQIQRgAUABY8N0CYMzpAmgCcAF4AIABYIgBhQKSAQEzmAEAoAEBsAEUwAEB2gEGCAEQARgB&sclient=gws-wiz-serp",
    "sampleCount" : 1,
    "errorCount" : 0,
    "errorPct" : 0.0,
    "meanResTime" : 1393.0,
    "medianResTime" : 1393.0,
    "minResTime" : 1393.0,
    "maxResTime" : 1393.0,
    "pct1ResTime" : 1393.0,
    "pct2ResTime" : 1393.0,
    "pct3ResTime" : 1393.0,
    "throughput" : 0.7178750897343863,
    "receivedKBytesPerSec" : 280.37018238513997,
    "sentKBytesPerSec" : 2.4522725233309406
  },
  "https://pharma-shop.tn/-11" : {
    "transaction" : "https://pharma-shop.tn/-11",
    "sampleCount" : 2,
    "errorCount" : 0,
    "errorPct" : 0.0,
    "meanResTime" : 104.0,
    "medianResTime" : 104.0,
    "minResTime" : 37.0,
    "maxResTime" : 171.0,
    "pct1ResTime" : 171.0,
    "pct2ResTime" : 171.0,
    "pct3ResTime" : 171.0,
    "throughput" : 0.2472799208704253,
    "receivedKBytesPerSec" : 10.624946873454501,
    "sentKBytesPerSec" : 0.19294595388229477
  },
  "https://pharma-shop.tn/-99" : {
    "transaction" : "https://pharma-shop.tn/-99",
    "sampleCount" : 2,
    "errorCount" : 0,
    "errorPct" : 0.0,
    "meanResTime" : 43.0,
    "medianResTime" : 43.0,
    "minResTime" : 40.0,
    "maxResTime" : 46.0,
    "pct1ResTime" : 46.0,
    "pct2ResTime" : 46.0,
    "pct3ResTime" : 46.0,
    "throughput" : 0.3104144032283098,
    "receivedKBytesPerSec" : 1.0055122807698278,
    "sentKBytesPerSec" : 0.25766820580474936
  },
  "https://pharma-shop.tn/-96" : {
    "transaction" : "https://pharma-shop.tn/-96",
    "sampleCount" : 2,
    "errorCount" : 0,
    "errorPct" : 0.0,
    "meanResTime" : 42.0,
    "medianResTime" : 42.0,
    "minResTime" : 38.0,
    "maxResTime" : 46.0,
    "pct1ResTime" : 46.0,
    "pct2ResTime" : 46.0,
    "pct3ResTime" : 46.0,
    "throughput" : 0.311284046692607,
    "receivedKBytesPerSec" : 0.5985530155642024,
    "sentKBytesPerSec" : 0.2544382295719844
  },
  "https://pharma-shop.tn/-97" : {
    "transaction" : "https://pharma-shop.tn/-97",
    "sampleCount" : 2,
    "errorCount" : 0,
    "errorPct" : 0.0,
    "meanResTime" : 38.5,
    "medianResTime" : 38.5,
    "minResTime" : 33.0,
    "maxResTime" : 44.0,
    "pct1ResTime" : 44.0,
    "pct2ResTime" : 44.0,
    "pct3ResTime" : 44.0,
    "throughput" : 0.3114779629341224,
    "receivedKBytesPerSec" : 0.6597614273477651,
    "sentKBytesPerSec" : 0.2570301549602865
  },
  "https://pharma-shop.tn/-14" : {
    "transaction" : "https://pharma-shop.tn/-14",
    "sampleCount" : 2,
    "errorCount" : 0,
    "errorPct" : 0.0,
    "meanResTime" : 200.5,
    "medianResTime" : 200.5,
    "minResTime" : 37.0,
    "maxResTime" : 364.0,
    "pct1ResTime" : 364.0,
    "pct2ResTime" : 364.0,
    "pct3ResTime" : 364.0,
    "throughput" : 0.2486634340420241,
    "receivedKBytesPerSec" : 13.557863786833272,
    "sentKBytesPerSec" : 0.19621099092378466
  },
  "https://pharma-shop.tn/-15" : {
    "transaction" : "https://pharma-shop.tn/-15",
    "sampleCount" : 2,
    "errorCount" : 0,
    "errorPct" : 0.0,
    "meanResTime" : 131.5,
    "medianResTime" : 131.5,
    "minResTime" : 35.0,
    "maxResTime" : 228.0,
    "pct1ResTime" : 228.0,
    "pct2ResTime" : 228.0,
    "pct3ResTime" : 228.0,
    "throughput" : 0.25163563160543534,
    "receivedKBytesPerSec" : 12.212437484272773,
    "sentKBytesPerSec" : 0.1958531234272773
  },
  "https://pharma-shop.tn/-12" : {
    "transaction" : "https://pharma-shop.tn/-12",
    "sampleCount" : 2,
    "errorCount" : 0,
    "errorPct" : 0.0,
    "meanResTime" : 136.0,
    "medianResTime" : 136.0,
    "minResTime" : 39.0,
    "maxResTime" : 233.0,
    "pct1ResTime" : 233.0,
    "pct2ResTime" : 233.0,
    "pct3ResTime" : 233.0,
    "throughput" : 0.2476166893648632,
    "receivedKBytesPerSec" : 14.611319177912591,
    "sentKBytesPerSec" : 0.19369235173950725
  },
  "https://pharma-shop.tn/-13" : {
    "transaction" : "https://pharma-shop.tn/-13",
    "sampleCount" : 2,
    "errorCount" : 0,
    "errorPct" : 0.0,
    "meanResTime" : 152.5,
    "medianResTime" : 152.5,
    "minResTime" : 38.0,
    "maxResTime" : 267.0,
    "pct1ResTime" : 267.0,
    "pct2ResTime" : 267.0,
    "pct3ResTime" : 267.0,
    "throughput" : 0.24715768660405335,
    "receivedKBytesPerSec" : 11.58660270174246,
    "sentKBytesPerSec" : 0.19285057773109243
  },
  "https://pharma-shop.tn/-18" : {
    "transaction" : "https://pharma-shop.tn/-18",
    "sampleCount" : 2,
    "errorCount" : 0,
    "errorPct" : 0.0,
    "meanResTime" : 204.0,
    "medianResTime" : 204.0,
    "minResTime" : 39.0,
    "maxResTime" : 369.0,
    "pct1ResTime" : 369.0,
    "pct2ResTime" : 369.0,
    "pct3ResTime" : 369.0,
    "throughput" : 0.25559105431309903,
    "receivedKBytesPerSec" : 12.872279353035143,
    "sentKBytesPerSec" : 0.20142771565495207
  },
  "https://pharma-shop.tn/-19" : {
    "transaction" : "https://pharma-shop.tn/-19",
    "sampleCount" : 2,
    "errorCount" : 0,
    "errorPct" : 0.0,
    "meanResTime" : 156.5,
    "medianResTime" : 156.5,
    "minResTime" : 38.0,
    "maxResTime" : 275.0,
    "pct1ResTime" : 275.0,
    "pct2ResTime" : 275.0,
    "pct3ResTime" : 275.0,
    "throughput" : 0.25786487880350695,
    "receivedKBytesPerSec" : 24.409277897756574,
    "sentKBytesPerSec" : 0.2190844185146983
  },
  "https://pharma-shop.tn/-16" : {
    "transaction" : "https://pharma-shop.tn/-16",
    "sampleCount" : 2,
    "errorCount" : 0,
    "errorPct" : 0.0,
    "meanResTime" : 145.0,
    "medianResTime" : 145.0,
    "minResTime" : 37.0,
    "maxResTime" : 253.0,
    "pct1ResTime" : 253.0,
    "pct2ResTime" : 253.0,
    "pct3ResTime" : 253.0,
    "throughput" : 0.254000508001016,
    "receivedKBytesPerSec" : 15.021996840868683,
    "sentKBytesPerSec" : 0.198189849504699
  },
  "https://pharma-shop.tn/-17" : {
    "transaction" : "https://pharma-shop.tn/-17",
    "sampleCount" : 2,
    "errorCount" : 0,
    "errorPct" : 0.0,
    "meanResTime" : 146.5,
    "medianResTime" : 146.5,
    "minResTime" : 35.0,
    "maxResTime" : 258.0,
    "pct1ResTime" : 258.0,
    "pct2ResTime" : 258.0,
    "pct3ResTime" : 258.0,
    "throughput" : 0.2554278416347382,
    "receivedKBytesPerSec" : 10.051858836206897,
    "sentKBytesPerSec" : 0.1995530012771392
  },
  "https://pharma-shop.tn/-80" : {
    "transaction" : "https://pharma-shop.tn/-80",
    "sampleCount" : 2,
    "errorCount" : 0,
    "errorPct" : 0.0,
    "meanResTime" : 36.0,
    "medianResTime" : 36.0,
    "minResTime" : 35.0,
    "maxResTime" : 37.0,
    "pct1ResTime" : 37.0,
    "pct2ResTime" : 37.0,
    "pct3ResTime" : 37.0,
    "throughput" : 0.3091190108191654,
    "receivedKBytesPerSec" : 0.6840465610510047,
    "sentKBytesPerSec" : 0.25236669242658427
  },
  "https://pharma-shop.tn/-83" : {
    "transaction" : "https://pharma-shop.tn/-83",
    "sampleCount" : 2,
    "errorCount" : 0,
    "errorPct" : 0.0,
    "meanResTime" : 43.0,
    "medianResTime" : 43.0,
    "minResTime" : 40.0,
    "maxResTime" : 46.0,
    "pct1ResTime" : 46.0,
    "pct2ResTime" : 46.0,
    "pct3ResTime" : 46.0,
    "throughput" : 0.30916679548616477,
    "receivedKBytesPerSec" : 1.0485705866439945,
    "sentKBytesPerSec" : 0.25904795949914977
  },
  "https://pharma-shop.tn/-84" : {
    "transaction" : "https://pharma-shop.tn/-84",
    "sampleCount" : 2,
    "errorCount" : 0,
    "errorPct" : 0.0,
    "meanResTime" : 37.0,
    "medianResTime" : 37.0,
    "minResTime" : 32.0,
    "maxResTime" : 42.0,
    "pct1ResTime" : 42.0,
    "pct2ResTime" : 42.0,
    "pct3ResTime" : 42.0,
    "throughput" : 0.30964545595293386,
    "receivedKBytesPerSec" : 0.8303578340300356,
    "sentKBytesPerSec" : 0.2564251432110234
  },
  "https://pharma-shop.tn/-81" : {
    "transaction" : "https://pharma-shop.tn/-81",
    "sampleCount" : 2,
    "errorCount" : 0,
    "errorPct" : 0.0,
    "meanResTime" : 43.5,
    "medianResTime" : 43.5,
    "minResTime" : 39.0,
    "maxResTime" : 48.0,
    "pct1ResTime" : 48.0,
    "pct2ResTime" : 48.0,
    "pct3ResTime" : 48.0,
    "throughput" : 0.3087849312953528,
    "receivedKBytesPerSec" : 2.0211240253975604,
    "sentKBytesPerSec" : 0.2590295468581133
  },
  "https://pharma-shop.tn/-82" : {
    "transaction" : "https://pharma-shop.tn/-82",
    "sampleCount" : 2,
    "errorCount" : 0,
    "errorPct" : 0.0,
    "meanResTime" : 45.5,
    "medianResTime" : 45.5,
    "minResTime" : 40.0,
    "maxResTime" : 51.0,
    "pct1ResTime" : 51.0,
    "pct2ResTime" : 51.0,
    "pct3ResTime" : 51.0,
    "throughput" : 0.3092624091541673,
    "receivedKBytesPerSec" : 1.0787942631823102,
    "sentKBytesPerSec" : 0.26094015772382867
  },
  "https://pharma-shop.tn/-87" : {
    "transaction" : "https://pharma-shop.tn/-87",
    "sampleCount" : 2,
    "errorCount" : 0,
    "errorPct" : 0.0,
    "meanResTime" : 47.5,
    "medianResTime" : 47.5,
    "minResTime" : 36.0,
    "maxResTime" : 59.0,
    "pct1ResTime" : 59.0,
    "pct2ResTime" : 59.0,
    "pct3ResTime" : 59.0,
    "throughput" : 0.31017369727047145,
    "receivedKBytesPerSec" : 2.3004044374224564,
    "sentKBytesPerSec" : 0.25928582506203474
  },
  "https://pharma-shop.tn/-88" : {
    "transaction" : "https://pharma-shop.tn/-88",
    "sampleCount" : 2,
    "errorCount" : 0,
    "errorPct" : 0.0,
    "meanResTime" : 37.0,
    "medianResTime" : 37.0,
    "minResTime" : 35.0,
    "maxResTime" : 39.0,
    "pct1ResTime" : 39.0,
    "pct2ResTime" : 39.0,
    "pct3ResTime" : 39.0,
    "throughput" : 0.30998140111593303,
    "receivedKBytesPerSec" : 1.4076303859268444,
    "sentKBytesPerSec" : 0.253373469466832
  },
  "https://pharma-shop.tn/-85" : {
    "transaction" : "https://pharma-shop.tn/-85",
    "sampleCount" : 2,
    "errorCount" : 0,
    "errorPct" : 0.0,
    "meanResTime" : 39.5,
    "medianResTime" : 39.5,
    "minResTime" : 38.0,
    "maxResTime" : 41.0,
    "pct1ResTime" : 41.0,
    "pct2ResTime" : 41.0,
    "pct3ResTime" : 41.0,
    "throughput" : 0.3093102381688834,
    "receivedKBytesPerSec" : 1.0632539437055366,
    "sentKBytesPerSec" : 0.2543351763068358
  },
  "https://pharma-shop.tn/-86" : {
    "transaction" : "https://pharma-shop.tn/-86",
    "sampleCount" : 2,
    "errorCount" : 0,
    "errorPct" : 0.0,
    "meanResTime" : 41.0,
    "medianResTime" : 41.0,
    "minResTime" : 34.0,
    "maxResTime" : 48.0,
    "pct1ResTime" : 48.0,
    "pct2ResTime" : 48.0,
    "pct3ResTime" : 48.0,
    "throughput" : 0.31022180859314413,
    "receivedKBytesPerSec" : 0.8073643749030557,
    "sentKBytesPerSec" : 0.26629391577477896
  },
  "https://pharma-shop.tn/-89" : {
    "transaction" : "https://pharma-shop.tn/-89",
    "sampleCount" : 2,
    "errorCount" : 0,
    "errorPct" : 0.0,
    "meanResTime" : 44.0,
    "medianResTime" : 44.0,
    "minResTime" : 33.0,
    "maxResTime" : 55.0,
    "pct1ResTime" : 55.0,
    "pct2ResTime" : 55.0,
    "pct3ResTime" : 55.0,
    "throughput" : 0.31007751937984496,
    "receivedKBytesPerSec" : 1.571281492248062,
    "sentKBytesPerSec" : 0.2549660852713178
  },
  "https://www.google-analytics.com/j/collect?v=1&_v=j99&a=382515470&t=pageview&_s=1&dl=https%3A%2F%2Fpharma-shop.tn%2F&ul=fr-fr&de=UTF-8&dt=Votre%20premi%C3%A8re%20parapharmacie%20en%20ligne%20en%20Tunisie&sd=24-bit&sr=1536x864&vp=1531x664&je=0&_u=AACAAEIJAAAAACAAI~&jid=&gjid=&cid=1966698233.1680104207&tid=UA-71713758-1&_gid=582023006.1680254087&_slc=1&did=d6YPbH&z=462389109" : {
    "transaction" : "https://www.google-analytics.com/j/collect?v=1&_v=j99&a=382515470&t=pageview&_s=1&dl=https%3A%2F%2Fpharma-shop.tn%2F&ul=fr-fr&de=UTF-8&dt=Votre%20premi%C3%A8re%20parapharmacie%20en%20ligne%20en%20Tunisie&sd=24-bit&sr=1536x864&vp=1531x664&je=0&_u=AACAAEIJAAAAACAAI~&jid=&gjid=&cid=1966698233.1680104207&tid=UA-71713758-1&_gid=582023006.1680254087&_slc=1&did=d6YPbH&z=462389109",
    "sampleCount" : 1,
    "errorCount" : 0,
    "errorPct" : 0.0,
    "meanResTime" : 40.0,
    "medianResTime" : 40.0,
    "minResTime" : 40.0,
    "maxResTime" : 40.0,
    "pct1ResTime" : 40.0,
    "pct2ResTime" : 40.0,
    "pct3ResTime" : 40.0,
    "throughput" : 25.0,
    "receivedKBytesPerSec" : 10.7421875,
    "sentKBytesPerSec" : 17.6025390625
  },
  "https://bootstrap.smartsuppchat.com/widget/b9690c990e4111de60bc2b144aa143172e19e795.json" : {
    "transaction" : "https://bootstrap.smartsuppchat.com/widget/b9690c990e4111de60bc2b144aa143172e19e795.json",
    "sampleCount" : 2,
    "errorCount" : 0,
    "errorPct" : 0.0,
    "meanResTime" : 190.0,
    "medianResTime" : 190.0,
    "minResTime" : 51.0,
    "maxResTime" : 329.0,
    "pct1ResTime" : 329.0,
    "pct2ResTime" : 329.0,
    "pct3ResTime" : 329.0,
    "throughput" : 0.35932446999640677,
    "receivedKBytesPerSec" : 0.3226551271110313,
    "sentKBytesPerSec" : 0.15720445562342797
  },
  "https://pharma-shop.tn/" : {
    "transaction" : "https://pharma-shop.tn/",
    "sampleCount" : 2,
    "errorCount" : 1,
    "errorPct" : 50.0,
    "meanResTime" : 2401.5,
    "medianResTime" : 2401.5,
    "minResTime" : 1407.0,
    "maxResTime" : 3396.0,
    "pct1ResTime" : 3396.0,
    "pct2ResTime" : 3396.0,
    "pct3ResTime" : 3396.0,
    "throughput" : 0.21249468763280918,
    "receivedKBytesPerSec" : 857.4495781648427,
    "sentKBytesPerSec" : 20.960401282936676
  },
  "https://pharma-shop.tn/-32" : {
    "transaction" : "https://pharma-shop.tn/-32",
    "sampleCount" : 2,
    "errorCount" : 0,
    "errorPct" : 0.0,
    "meanResTime" : 55.5,
    "medianResTime" : 55.5,
    "minResTime" : 33.0,
    "maxResTime" : 78.0,
    "pct1ResTime" : 78.0,
    "pct2ResTime" : 78.0,
    "pct3ResTime" : 78.0,
    "throughput" : 0.2796029637914162,
    "receivedKBytesPerSec" : 0.8587415245351602,
    "sentKBytesPerSec" : 0.23154620438976656
  },
  "https://pharma-shop.tn/-33" : {
    "transaction" : "https://pharma-shop.tn/-33",
    "sampleCount" : 2,
    "errorCount" : 0,
    "errorPct" : 0.0,
    "meanResTime" : 52.0,
    "medianResTime" : 52.0,
    "minResTime" : 35.0,
    "maxResTime" : 69.0,
    "pct1ResTime" : 69.0,
    "pct2ResTime" : 69.0,
    "pct3ResTime" : 69.0,
    "throughput" : 0.2796420581655481,
    "receivedKBytesPerSec" : 0.4683458298378076,
    "sentKBytesPerSec" : 0.24304827321029082
  },
  "https://pharma-shop.tn/-30" : {
    "transaction" : "https://pharma-shop.tn/-30",
    "sampleCount" : 2,
    "errorCount" : 0,
    "errorPct" : 0.0,
    "meanResTime" : 55.0,
    "medianResTime" : 55.0,
    "minResTime" : 39.0,
    "maxResTime" : 71.0,
    "pct1ResTime" : 71.0,
    "pct2ResTime" : 71.0,
    "pct3ResTime" : 71.0,
    "throughput" : 0.27797081306462823,
    "receivedKBytesPerSec" : 1.654659268589298,
    "sentKBytesPerSec" : 0.22693710910354412
  },
  "https://pharma-shop.tn/-31" : {
    "transaction" : "https://pharma-shop.tn/-31",
    "sampleCount" : 2,
    "errorCount" : 0,
    "errorPct" : 0.0,
    "meanResTime" : 49.0,
    "medianResTime" : 49.0,
    "minResTime" : 37.0,
    "maxResTime" : 61.0,
    "pct1ResTime" : 61.0,
    "pct2ResTime" : 61.0,
    "pct3ResTime" : 61.0,
    "throughput" : 0.2772002772002772,
    "receivedKBytesPerSec" : 0.7888296950796951,
    "sentKBytesPerSec" : 0.22982718295218296
  },
  "https://pharma-shop.tn/-36" : {
    "transaction" : "https://pharma-shop.tn/-36",
    "sampleCount" : 2,
    "errorCount" : 0,
    "errorPct" : 0.0,
    "meanResTime" : 47.0,
    "medianResTime" : 47.0,
    "minResTime" : 36.0,
    "maxResTime" : 58.0,
    "pct1ResTime" : 58.0,
    "pct2ResTime" : 58.0,
    "pct3ResTime" : 58.0,
    "throughput" : 0.28498147620404674,
    "receivedKBytesPerSec" : 0.771453761755486,
    "sentKBytesPerSec" : 0.23794840054146482
  },
  "https://pharma-shop.tn/-37" : {
    "transaction" : "https://pharma-shop.tn/-37",
    "sampleCount" : 2,
    "errorCount" : 0,
    "errorPct" : 0.0,
    "meanResTime" : 54.0,
    "medianResTime" : 54.0,
    "minResTime" : 38.0,
    "maxResTime" : 70.0,
    "pct1ResTime" : 70.0,
    "pct2ResTime" : 70.0,
    "pct3ResTime" : 70.0,
    "throughput" : 0.28421202216853775,
    "receivedKBytesPerSec" : 0.5700893491544693,
    "sentKBytesPerSec" : 0.23258757282933068
  },
  "https://pharma-shop.tn/-34" : {
    "transaction" : "https://pharma-shop.tn/-34",
    "sampleCount" : 2,
    "errorCount" : 0,
    "errorPct" : 0.0,
    "meanResTime" : 55.0,
    "medianResTime" : 55.0,
    "minResTime" : 36.0,
    "maxResTime" : 74.0,
    "pct1ResTime" : 74.0,
    "pct2ResTime" : 74.0,
    "pct3ResTime" : 74.0,
    "throughput" : 0.282326369282891,
    "receivedKBytesPerSec" : 0.4913140527950311,
    "sentKBytesPerSec" : 0.23518007128740825
  },
  "https://pharma-shop.tn/-35" : {
    "transaction" : "https://pharma-shop.tn/-35",
    "sampleCount" : 2,
    "errorCount" : 0,
    "errorPct" : 0.0,
    "meanResTime" : 57.0,
    "medianResTime" : 57.0,
    "minResTime" : 35.0,
    "maxResTime" : 79.0,
    "pct1ResTime" : 79.0,
    "pct2ResTime" : 79.0,
    "pct3ResTime" : 79.0,
    "throughput" : 0.2821272393849626,
    "receivedKBytesPerSec" : 0.9207707363520947,
    "sentKBytesPerSec" : 0.2341876498800959
  },
  "https://widget-v2.smartsuppcdn.com/asset-manifest.json" : {
    "transaction" : "https://widget-v2.smartsuppcdn.com/asset-manifest.json",
    "sampleCount" : 2,
    "errorCount" : 0,
    "errorPct" : 0.0,
    "meanResTime" : 119.5,
    "medianResTime" : 119.5,
    "minResTime" : 40.0,
    "maxResTime" : 199.0,
    "pct1ResTime" : 199.0,
    "pct2ResTime" : 199.0,
    "pct3ResTime" : 199.0,
    "throughput" : 0.37900322152738297,
    "receivedKBytesPerSec" : 0.5194638880992988,
    "sentKBytesPerSec" : 0.1589666832480576
  },
  "https://pharma-shop.tn/-38" : {
    "transaction" : "https://pharma-shop.tn/-38",
    "sampleCount" : 2,
    "errorCount" : 0,
    "errorPct" : 0.0,
    "meanResTime" : 54.5,
    "medianResTime" : 54.5,
    "minResTime" : 33.0,
    "maxResTime" : 76.0,
    "pct1ResTime" : 76.0,
    "pct2ResTime" : 76.0,
    "pct3ResTime" : 76.0,
    "throughput" : 0.28457598178713717,
    "receivedKBytesPerSec" : 0.5285776536710302,
    "sentKBytesPerSec" : 0.23510867245304498
  },
  "https://pharma-shop.tn/-39" : {
    "transaction" : "https://pharma-shop.tn/-39",
    "sampleCount" : 2,
    "errorCount" : 0,
    "errorPct" : 0.0,
    "meanResTime" : 56.0,
    "medianResTime" : 56.0,
    "minResTime" : 37.0,
    "maxResTime" : 75.0,
    "pct1ResTime" : 75.0,
    "pct2ResTime" : 75.0,
    "pct3ResTime" : 75.0,
    "throughput" : 0.286286859433152,
    "receivedKBytesPerSec" : 0.8068592542227312,
    "sentKBytesPerSec" : 0.2331672273117664
  },
  "https://www.google.com/complete/search?q&cp=0&client=gws-wiz-serp&xssi=t&hl=fr-TN&authuser=0&pq=pharmashop&psi=iKUmZPv1G7ypkdUP4pSpgAo.1680254346734&dpr=1.25" : {
    "transaction" : "https://www.google.com/complete/search?q&cp=0&client=gws-wiz-serp&xssi=t&hl=fr-TN&authuser=0&pq=pharmashop&psi=iKUmZPv1G7ypkdUP4pSpgAo.1680254346734&dpr=1.25",
    "sampleCount" : 1,
    "errorCount" : 0,
    "errorPct" : 0.0,
    "meanResTime" : 115.0,
    "medianResTime" : 115.0,
    "minResTime" : 115.0,
    "maxResTime" : 115.0,
    "pct1ResTime" : 115.0,
    "pct2ResTime" : 115.0,
    "pct3ResTime" : 115.0,
    "throughput" : 8.695652173913043,
    "receivedKBytesPerSec" : 25.509510869565215,
    "sentKBytesPerSec" : 8.772078804347826
  },
  "https://pharma-shop.tn/-21" : {
    "transaction" : "https://pharma-shop.tn/-21",
    "sampleCount" : 2,
    "errorCount" : 0,
    "errorPct" : 0.0,
    "meanResTime" : 223.0,
    "medianResTime" : 223.0,
    "minResTime" : 44.0,
    "maxResTime" : 402.0,
    "pct1ResTime" : 402.0,
    "pct2ResTime" : 402.0,
    "pct3ResTime" : 402.0,
    "throughput" : 0.2609943886206446,
    "receivedKBytesPerSec" : 43.98392641589456,
    "sentKBytesPerSec" : 0.21792011940493278
  },
  "https://pharma-shop.tn/-22" : {
    "transaction" : "https://pharma-shop.tn/-22",
    "sampleCount" : 2,
    "errorCount" : 0,
    "errorPct" : 0.0,
    "meanResTime" : 681.0,
    "medianResTime" : 681.0,
    "minResTime" : 34.0,
    "maxResTime" : 1328.0,
    "pct1ResTime" : 1328.0,
    "pct2ResTime" : 1328.0,
    "pct3ResTime" : 1328.0,
    "throughput" : 0.2630194634402946,
    "receivedKBytesPerSec" : 248.58421554445027,
    "sentKBytesPerSec" : 0.22269323711204628
  },
  "https://pharma-shop.tn/-20" : {
    "transaction" : "https://pharma-shop.tn/-20",
    "sampleCount" : 2,
    "errorCount" : 0,
    "errorPct" : 0.0,
    "meanResTime" : 302.0,
    "medianResTime" : 302.0,
    "minResTime" : 36.0,
    "maxResTime" : 568.0,
    "pct1ResTime" : 568.0,
    "pct2ResTime" : 568.0,
    "pct3ResTime" : 568.0,
    "throughput" : 0.259302476338649,
    "receivedKBytesPerSec" : 42.37873557629975,
    "sentKBytesPerSec" : 0.2170138888888889
  },
  "https://pharma-shop.tn/-25" : {
    "transaction" : "https://pharma-shop.tn/-25",
    "sampleCount" : 2,
    "errorCount" : 0,
    "errorPct" : 0.0,
    "meanResTime" : 75.0,
    "medianResTime" : 75.0,
    "minResTime" : 33.0,
    "maxResTime" : 117.0,
    "pct1ResTime" : 117.0,
    "pct2ResTime" : 117.0,
    "pct3ResTime" : 117.0,
    "throughput" : 0.26986911347996223,
    "receivedKBytesPerSec" : 11.0887479338146,
    "sentKBytesPerSec" : 0.2271749763864526
  },
  "https://pharma-shop.tn/-26" : {
    "transaction" : "https://pharma-shop.tn/-26",
    "sampleCount" : 2,
    "errorCount" : 0,
    "errorPct" : 0.0,
    "meanResTime" : 48.5,
    "medianResTime" : 48.5,
    "minResTime" : 42.0,
    "maxResTime" : 55.0,
    "pct1ResTime" : 55.0,
    "pct2ResTime" : 55.0,
    "pct3ResTime" : 55.0,
    "throughput" : 0.27386005751061204,
    "receivedKBytesPerSec" : 0.6025456148158291,
    "sentKBytesPerSec" : 0.22491826988908667
  },
  "https://pharma-shop.tn/-23" : {
    "transaction" : "https://pharma-shop.tn/-23",
    "sampleCount" : 2,
    "errorCount" : 0,
    "errorPct" : 0.0,
    "meanResTime" : 648.0,
    "medianResTime" : 648.0,
    "minResTime" : 41.0,
    "maxResTime" : 1255.0,
    "pct1ResTime" : 1255.0,
    "pct2ResTime" : 1255.0,
    "pct3ResTime" : 1255.0,
    "throughput" : 0.26705835224996666,
    "receivedKBytesPerSec" : 113.91838237748698,
    "sentKBytesPerSec" : 0.22611288222726666
  },
  "https://pharma-shop.tn/-24" : {
    "transaction" : "https://pharma-shop.tn/-24",
    "sampleCount" : 2,
    "errorCount" : 0,
    "errorPct" : 0.0,
    "meanResTime" : 68.5,
    "medianResTime" : 68.5,
    "minResTime" : 36.0,
    "maxResTime" : 101.0,
    "pct1ResTime" : 101.0,
    "pct2ResTime" : 101.0,
    "pct3ResTime" : 101.0,
    "throughput" : 0.2669870511280203,
    "receivedKBytesPerSec" : 2.9459830963823257,
    "sentKBytesPerSec" : 0.22188084034174343
  },
  "https://pharma-shop.tn/-29" : {
    "transaction" : "https://pharma-shop.tn/-29",
    "sampleCount" : 2,
    "errorCount" : 0,
    "errorPct" : 0.0,
    "meanResTime" : 140.5,
    "medianResTime" : 140.5,
    "minResTime" : 35.0,
    "maxResTime" : 246.0,
    "pct1ResTime" : 246.0,
    "pct2ResTime" : 246.0,
    "pct3ResTime" : 246.0,
    "throughput" : 0.27696994876055947,
    "receivedKBytesPerSec" : 21.781495594446753,
    "sentKBytesPerSec" : 0.23017717421409778
  },
  "https://pharma-shop.tn/-27" : {
    "transaction" : "https://pharma-shop.tn/-27",
    "sampleCount" : 2,
    "errorCount" : 0,
    "errorPct" : 0.0,
    "meanResTime" : 55.0,
    "medianResTime" : 55.0,
    "minResTime" : 35.0,
    "maxResTime" : 75.0,
    "pct1ResTime" : 75.0,
    "pct2ResTime" : 75.0,
    "pct3ResTime" : 75.0,
    "throughput" : 0.27434842249657065,
    "receivedKBytesPerSec" : 0.6972575874485597,
    "sentKBytesPerSec" : 0.2285343792866941
  },
  "https://pharma-shop.tn/-28" : {
    "transaction" : "https://pharma-shop.tn/-28",
    "sampleCount" : 2,
    "errorCount" : 0,
    "errorPct" : 0.0,
    "meanResTime" : 51.5,
    "medianResTime" : 51.5,
    "minResTime" : 44.0,
    "maxResTime" : 59.0,
    "pct1ResTime" : 59.0,
    "pct2ResTime" : 59.0,
    "pct3ResTime" : 59.0,
    "throughput" : 0.27559597629874605,
    "receivedKBytesPerSec" : 0.6522527817968858,
    "sentKBytesPerSec" : 0.2295736013504203
  },
  "https://www.google-analytics.com/j/collect?v=1&_v=j99&a=1576582099&t=pageview&_s=1&dl=https%3A%2F%2Fpharma-shop.tn%2F&dr=https%3A%2F%2Fwww.google.com%2F&ul=fr-fr&de=UTF-8&dt=Votre%20premi%C3%A8re%20parapharmacie%20en%20ligne%20en%20Tunisie&sd=24-bit&sr=1536x864&vp=1531x664&je=0&_u=AACAAEIJAAAAACAAI~&jid=473753450&gjid=218319513&cid=1966698233.1680104207&tid=UA-71713758-1&_gid=582023006.1680254087&_r=1&_slc=1&did=d6YPbH&z=443076985" : {
    "transaction" : "https://www.google-analytics.com/j/collect?v=1&_v=j99&a=1576582099&t=pageview&_s=1&dl=https%3A%2F%2Fpharma-shop.tn%2F&dr=https%3A%2F%2Fwww.google.com%2F&ul=fr-fr&de=UTF-8&dt=Votre%20premi%C3%A8re%20parapharmacie%20en%20ligne%20en%20Tunisie&sd=24-bit&sr=1536x864&vp=1531x664&je=0&_u=AACAAEIJAAAAACAAI~&jid=473753450&gjid=218319513&cid=1966698233.1680104207&tid=UA-71713758-1&_gid=582023006.1680254087&_r=1&_slc=1&did=d6YPbH&z=443076985",
    "sampleCount" : 1,
    "errorCount" : 0,
    "errorPct" : 0.0,
    "meanResTime" : 143.0,
    "medianResTime" : 143.0,
    "minResTime" : 143.0,
    "maxResTime" : 143.0,
    "pct1ResTime" : 143.0,
    "pct2ResTime" : 143.0,
    "pct3ResTime" : 143.0,
    "throughput" : 6.993006993006993,
    "receivedKBytesPerSec" : 3.0048076923076925,
    "sentKBytesPerSec" : 5.326704545454546
  },
  "https://pharma-shop.tn/-50" : {
    "transaction" : "https://pharma-shop.tn/-50",
    "sampleCount" : 2,
    "errorCount" : 0,
    "errorPct" : 0.0,
    "meanResTime" : 70.5,
    "medianResTime" : 70.5,
    "minResTime" : 43.0,
    "maxResTime" : 98.0,
    "pct1ResTime" : 98.0,
    "pct2ResTime" : 98.0,
    "pct3ResTime" : 98.0,
    "throughput" : 0.2948547840188707,
    "receivedKBytesPerSec" : 0.6262784719150818,
    "sentKBytesPerSec" : 0.24590428276573786
  },
  "https://pharma-shop.tn/-51" : {
    "transaction" : "https://pharma-shop.tn/-51",
    "sampleCount" : 2,
    "errorCount" : 0,
    "errorPct" : 0.0,
    "meanResTime" : 70.0,
    "medianResTime" : 70.0,
    "minResTime" : 36.0,
    "maxResTime" : 104.0,
    "pct1ResTime" : 104.0,
    "pct2ResTime" : 104.0,
    "pct3ResTime" : 104.0,
    "throughput" : 0.29691211401425177,
    "receivedKBytesPerSec" : 0.42710111713182897,
    "sentKBytesPerSec" : 0.2467502041270784
  },
  "https://pharma-shop.tn/-54" : {
    "transaction" : "https://pharma-shop.tn/-54",
    "sampleCount" : 2,
    "errorCount" : 0,
    "errorPct" : 0.0,
    "meanResTime" : 94.5,
    "medianResTime" : 94.5,
    "minResTime" : 37.0,
    "maxResTime" : 152.0,
    "pct1ResTime" : 152.0,
    "pct2ResTime" : 152.0,
    "pct3ResTime" : 152.0,
    "throughput" : 0.30111412225233364,
    "receivedKBytesPerSec" : 1.1729924156880458,
    "sentKBytesPerSec" : 0.2475957919301415
  },
  "https://pharma-shop.tn/-55" : {
    "transaction" : "https://pharma-shop.tn/-55",
    "sampleCount" : 2,
    "errorCount" : 0,
    "errorPct" : 0.0,
    "meanResTime" : 92.5,
    "medianResTime" : 92.5,
    "minResTime" : 34.0,
    "maxResTime" : 151.0,
    "pct1ResTime" : 151.0,
    "pct2ResTime" : 151.0,
    "pct3ResTime" : 151.0,
    "throughput" : 0.3011594639361542,
    "receivedKBytesPerSec" : 1.511973441499774,
    "sentKBytesPerSec" : 0.24645667068212618
  },
  "https://pharma-shop.tn/-52" : {
    "transaction" : "https://pharma-shop.tn/-52",
    "sampleCount" : 2,
    "errorCount" : 0,
    "errorPct" : 0.0,
    "meanResTime" : 68.5,
    "medianResTime" : 68.5,
    "minResTime" : 39.0,
    "maxResTime" : 98.0,
    "pct1ResTime" : 98.0,
    "pct2ResTime" : 98.0,
    "pct3ResTime" : 98.0,
    "throughput" : 0.2971768202080238,
    "receivedKBytesPerSec" : 0.5235419762258543,
    "sentKBytesPerSec" : 0.2437778603268945
  },
  "https://pharma-shop.tn/-53" : {
    "transaction" : "https://pharma-shop.tn/-53",
    "sampleCount" : 2,
    "errorCount" : 0,
    "errorPct" : 0.0,
    "meanResTime" : 125.0,
    "medianResTime" : 125.0,
    "minResTime" : 40.0,
    "maxResTime" : 210.0,
    "pct1ResTime" : 210.0,
    "pct2ResTime" : 210.0,
    "pct3ResTime" : 210.0,
    "throughput" : 0.29868578255675027,
    "receivedKBytesPerSec" : 2.8278893182497016,
    "sentKBytesPerSec" : 0.24851590501792115
  },
  "https://pharma-shop.tn/-58" : {
    "transaction" : "https://pharma-shop.tn/-58",
    "sampleCount" : 2,
    "errorCount" : 0,
    "errorPct" : 0.0,
    "meanResTime" : 45.0,
    "medianResTime" : 45.0,
    "minResTime" : 36.0,
    "maxResTime" : 54.0,
    "pct1ResTime" : 54.0,
    "pct2ResTime" : 54.0,
    "pct3ResTime" : 54.0,
    "throughput" : 0.3069838833461243,
    "receivedKBytesPerSec" : 0.9446349769762088,
    "sentKBytesPerSec" : 0.25152292785878744
  },
  "https://pharma-shop.tn/-59" : {
    "transaction" : "https://pharma-shop.tn/-59",
    "sampleCount" : 2,
    "errorCount" : 0,
    "errorPct" : 0.0,
    "meanResTime" : 44.0,
    "medianResTime" : 44.0,
    "minResTime" : 35.0,
    "maxResTime" : 53.0,
    "pct1ResTime" : 53.0,
    "pct2ResTime" : 53.0,
    "pct3ResTime" : 53.0,
    "throughput" : 0.307455803228286,
    "receivedKBytesPerSec" : 0.8698236933128363,
    "sentKBytesPerSec" : 0.25671358570330516
  },
  "https://pharma-shop.tn/-56" : {
    "transaction" : "https://pharma-shop.tn/-56",
    "sampleCount" : 2,
    "errorCount" : 0,
    "errorPct" : 0.0,
    "meanResTime" : 37.5,
    "medianResTime" : 37.5,
    "minResTime" : 34.0,
    "maxResTime" : 41.0,
    "pct1ResTime" : 41.0,
    "pct2ResTime" : 41.0,
    "pct3ResTime" : 41.0,
    "throughput" : 0.3071253071253071,
    "receivedKBytesPerSec" : 0.916877015509828,
    "sentKBytesPerSec" : 0.2555378531941032
  },
  "https://pharma-shop.tn/-57" : {
    "transaction" : "https://pharma-shop.tn/-57",
    "sampleCount" : 2,
    "errorCount" : 0,
    "errorPct" : 0.0,
    "meanResTime" : 47.0,
    "medianResTime" : 47.0,
    "minResTime" : 37.0,
    "maxResTime" : 57.0,
    "pct1ResTime" : 57.0,
    "pct2ResTime" : 57.0,
    "pct3ResTime" : 57.0,
    "throughput" : 0.30703101013202333,
    "receivedKBytesPerSec" : 0.9426811482959778,
    "sentKBytesPerSec" : 0.25845774485723055
  },
  "Test" : {
    "transaction" : "Test",
    "sampleCount" : 1,
    "errorCount" : 1,
    "errorPct" : 100.0,
    "meanResTime" : 9019.0,
    "medianResTime" : 9019.0,
    "minResTime" : 9019.0,
    "maxResTime" : 9019.0,
    "pct1ResTime" : 9019.0,
    "pct2ResTime" : 9019.0,
    "pct3ResTime" : 9019.0,
    "throughput" : 0.11087703736556159,
    "receivedKBytesPerSec" : 941.3523273783125,
    "sentKBytesPerSec" : 23.318610364231066
  },
  "https://translations.smartsuppcdn.com/api/v1/widget/translations/lang/fr/defaults" : {
    "transaction" : "https://translations.smartsuppcdn.com/api/v1/widget/translations/lang/fr/defaults",
    "sampleCount" : 2,
    "errorCount" : 0,
    "errorPct" : 0.0,
    "meanResTime" : 118.5,
    "medianResTime" : 118.5,
    "minResTime" : 35.0,
    "maxResTime" : 202.0,
    "pct1ResTime" : 202.0,
    "pct2ResTime" : 202.0,
    "pct3ResTime" : 202.0,
    "throughput" : 0.39123630672926446,
    "receivedKBytesPerSec" : 1.3586292057902973,
    "sentKBytesPerSec" : 0.15607424931533645
  },
  "https://pharma-shop.tn/-40" : {
    "transaction" : "https://pharma-shop.tn/-40",
    "sampleCount" : 2,
    "errorCount" : 0,
    "errorPct" : 0.0,
    "meanResTime" : 65.5,
    "medianResTime" : 65.5,
    "minResTime" : 39.0,
    "maxResTime" : 92.0,
    "pct1ResTime" : 92.0,
    "pct2ResTime" : 92.0,
    "pct3ResTime" : 92.0,
    "throughput" : 0.28665615594094884,
    "receivedKBytesPerSec" : 0.3773559552816397,
    "sentKBytesPerSec" : 0.23486769026802348
  },
  "https://pharma-shop.tn/-43" : {
    "transaction" : "https://pharma-shop.tn/-43",
    "sampleCount" : 2,
    "errorCount" : 0,
    "errorPct" : 0.0,
    "meanResTime" : 49.0,
    "medianResTime" : 49.0,
    "minResTime" : 33.0,
    "maxResTime" : 65.0,
    "pct1ResTime" : 65.0,
    "pct2ResTime" : 65.0,
    "pct3ResTime" : 65.0,
    "throughput" : 0.2898130705694827,
    "receivedKBytesPerSec" : 0.569154379800029,
    "sentKBytesPerSec" : 0.24141655194899292
  },
  "https://pharma-shop.tn/-44" : {
    "transaction" : "https://pharma-shop.tn/-44",
    "sampleCount" : 2,
    "errorCount" : 0,
    "errorPct" : 0.0,
    "meanResTime" : 51.5,
    "medianResTime" : 51.5,
    "minResTime" : 34.0,
    "maxResTime" : 69.0,
    "pct1ResTime" : 69.0,
    "pct2ResTime" : 69.0,
    "pct3ResTime" : 69.0,
    "throughput" : 0.2901494269548818,
    "receivedKBytesPerSec" : 0.7024222943565936,
    "sentKBytesPerSec" : 0.24113004134629334
  },
  "https://stats.g.doubleclick.net/j/collect?t=dc&aip=1&_r=3&v=1&_v=j99&tid=UA-71713758-1&cid=1966698233.1680104207&jid=473753450&gjid=218319513&_gid=582023006.1680254087&_u=AACAAEIIAAAAACAAI~&z=1446073229" : {
    "transaction" : "https://stats.g.doubleclick.net/j/collect?t=dc&aip=1&_r=3&v=1&_v=j99&tid=UA-71713758-1&cid=1966698233.1680104207&jid=473753450&gjid=218319513&_gid=582023006.1680254087&_u=AACAAEIIAAAAACAAI~&z=1446073229",
    "sampleCount" : 1,
    "errorCount" : 0,
    "errorPct" : 0.0,
    "meanResTime" : 192.0,
    "medianResTime" : 192.0,
    "minResTime" : 192.0,
    "maxResTime" : 192.0,
    "pct1ResTime" : 192.0,
    "pct2ResTime" : 192.0,
    "pct3ResTime" : 192.0,
    "throughput" : 5.208333333333333,
    "receivedKBytesPerSec" : 2.6092529296875,
    "sentKBytesPerSec" : 2.8483072916666665
  },
  "https://pharma-shop.tn/-41" : {
    "transaction" : "https://pharma-shop.tn/-41",
    "sampleCount" : 2,
    "errorCount" : 0,
    "errorPct" : 0.0,
    "meanResTime" : 66.0,
    "medianResTime" : 66.0,
    "minResTime" : 36.0,
    "maxResTime" : 96.0,
    "pct1ResTime" : 96.0,
    "pct2ResTime" : 96.0,
    "pct3ResTime" : 96.0,
    "throughput" : 0.2869852202611566,
    "receivedKBytesPerSec" : 0.5834992466637968,
    "sentKBytesPerSec" : 0.23597808150380253
  },
  "https://pharma-shop.tn/-42" : {
    "transaction" : "https://pharma-shop.tn/-42",
    "sampleCount" : 2,
    "errorCount" : 0,
    "errorPct" : 0.0,
    "meanResTime" : 57.0,
    "medianResTime" : 57.0,
    "minResTime" : 35.0,
    "maxResTime" : 79.0,
    "pct1ResTime" : 79.0,
    "pct2ResTime" : 79.0,
    "pct3ResTime" : 79.0,
    "throughput" : 0.2891008962127783,
    "receivedKBytesPerSec" : 0.5652148381034982,
    "sentKBytesPerSec" : 0.2425172557097427
  },
  "https://pharma-shop.tn/-47" : {
    "transaction" : "https://pharma-shop.tn/-47",
    "sampleCount" : 2,
    "errorCount" : 0,
    "errorPct" : 0.0,
    "meanResTime" : 59.0,
    "medianResTime" : 59.0,
    "minResTime" : 35.0,
    "maxResTime" : 83.0,
    "pct1ResTime" : 83.0,
    "pct2ResTime" : 83.0,
    "pct3ResTime" : 83.0,
    "throughput" : 0.2924831822170225,
    "receivedKBytesPerSec" : 0.8000443294823048,
    "sentKBytesPerSec" : 0.23964198230476746
  },
  "https://pharma-shop.tn/-48" : {
    "transaction" : "https://pharma-shop.tn/-48",
    "sampleCount" : 2,
    "errorCount" : 0,
    "errorPct" : 0.0,
    "meanResTime" : 61.5,
    "medianResTime" : 61.5,
    "minResTime" : 37.0,
    "maxResTime" : 86.0,
    "pct1ResTime" : 86.0,
    "pct2ResTime" : 86.0,
    "pct3ResTime" : 86.0,
    "throughput" : 0.29433406916850624,
    "receivedKBytesPerSec" : 0.8030951066961001,
    "sentKBytesPerSec" : 0.24259565857247978
  },
  "https://pharma-shop.tn/-45" : {
    "transaction" : "https://pharma-shop.tn/-45",
    "sampleCount" : 2,
    "errorCount" : 0,
    "errorPct" : 0.0,
    "meanResTime" : 58.0,
    "medianResTime" : 58.0,
    "minResTime" : 36.0,
    "maxResTime" : 80.0,
    "pct1ResTime" : 80.0,
    "pct2ResTime" : 80.0,
    "pct3ResTime" : 80.0,
    "throughput" : 0.29129041654529564,
    "receivedKBytesPerSec" : 1.1264746577337605,
    "sentKBytesPerSec" : 0.2375268533352753
  },
  "https://pharma-shop.tn/-46" : {
    "transaction" : "https://pharma-shop.tn/-46",
    "sampleCount" : 2,
    "errorCount" : 0,
    "errorPct" : 0.0,
    "meanResTime" : 53.5,
    "medianResTime" : 53.5,
    "minResTime" : 35.0,
    "maxResTime" : 72.0,
    "pct1ResTime" : 72.0,
    "pct2ResTime" : 72.0,
    "pct3ResTime" : 72.0,
    "throughput" : 0.29180040852057193,
    "receivedKBytesPerSec" : 1.0677501276626786,
    "sentKBytesPerSec" : 0.2487712467172454
  },
  "https://www.google.com/search?q=pharmashop&rlz=1C1PNJJ_frTN1050TN1050&sxsrf=APwXEdcSiZBW1PpYTEzwUR_yEox7_u6fbg%3A1680254294624&ei=VqUmZILfJemrkdUP7PyLkAk&oq=pha&gs_lcp=Cgxnd3Mtd2l6LXNlcnAQAxgAMgQIIxAnMgoIABCKBRCxAxBDMg0IABCKBRCxAxDJAxBDMggIABCABBCSAzIICAAQgAQQkgMyBwgAEIoFEEMyBwgAEIoFEEMyBwgAEIoFEEMyBwgAEIoFEEMyBwguEIoFEEM6BwgjEOoCECc6DQguEMcBENEDEOoCECc6DwgAEIoFEOoCELQCEEMYAToPCC4QigUQ6gIQtAIQQxgBOgsIABCABBCxAxCDAToICC4QgAQQsQM6CwgAEIoFELEDEIMBSgQIQRgAUABY8N0CYMzpAmgCcAF4AIABYIgBhQKSAQEzmAEAoAEBsAEUwAEB2gEGCAEQARgB&sclient=gws-wiz-serp-1" : {
    "transaction" : "https://www.google.com/search?q=pharmashop&rlz=1C1PNJJ_frTN1050TN1050&sxsrf=APwXEdcSiZBW1PpYTEzwUR_yEox7_u6fbg%3A1680254294624&ei=VqUmZILfJemrkdUP7PyLkAk&oq=pha&gs_lcp=Cgxnd3Mtd2l6LXNlcnAQAxgAMgQIIxAnMgoIABCKBRCxAxBDMg0IABCKBRCxAxDJAxBDMggIABCABBCSAzIICAAQgAQQkgMyBwgAEIoFEEMyBwgAEIoFEEMyBwgAEIoFEEMyBwgAEIoFEEMyBwguEIoFEEM6BwgjEOoCECc6DQguEMcBENEDEOoCECc6DwgAEIoFEOoCELQCEEMYAToPCC4QigUQ6gIQtAIQQxgBOgsIABCABBCxAxCDAToICC4QgAQQsQM6CwgAEIoFELEDEIMBSgQIQRgAUABY8N0CYMzpAmgCcAF4AIABYIgBhQKSAQEzmAEAoAEBsAEUwAEB2gEGCAEQARgB&sclient=gws-wiz-serp-1",
    "sampleCount" : 1,
    "errorCount" : 0,
    "errorPct" : 0.0,
    "meanResTime" : 46.0,
    "medianResTime" : 46.0,
    "minResTime" : 46.0,
    "maxResTime" : 46.0,
    "pct1ResTime" : 46.0,
    "pct2ResTime" : 46.0,
    "pct3ResTime" : 46.0,
    "throughput" : 21.73913043478261,
    "receivedKBytesPerSec" : 95.17238451086956,
    "sentKBytesPerSec" : 23.77717391304348
  },
  "https://www.google.com/search?q=pharmashop&rlz=1C1PNJJ_frTN1050TN1050&sxsrf=APwXEdcSiZBW1PpYTEzwUR_yEox7_u6fbg%3A1680254294624&ei=VqUmZILfJemrkdUP7PyLkAk&oq=pha&gs_lcp=Cgxnd3Mtd2l6LXNlcnAQAxgAMgQIIxAnMgoIABCKBRCxAxBDMg0IABCKBRCxAxDJAxBDMggIABCABBCSAzIICAAQgAQQkgMyBwgAEIoFEEMyBwgAEIoFEEMyBwgAEIoFEEMyBwgAEIoFEEMyBwguEIoFEEM6BwgjEOoCECc6DQguEMcBENEDEOoCECc6DwgAEIoFEOoCELQCEEMYAToPCC4QigUQ6gIQtAIQQxgBOgsIABCABBCxAxCDAToICC4QgAQQsQM6CwgAEIoFELEDEIMBSgQIQRgAUABY8N0CYMzpAmgCcAF4AIABYIgBhQKSAQEzmAEAoAEBsAEUwAEB2gEGCAEQARgB&sclient=gws-wiz-serp-2" : {
    "transaction" : "https://www.google.com/search?q=pharmashop&rlz=1C1PNJJ_frTN1050TN1050&sxsrf=APwXEdcSiZBW1PpYTEzwUR_yEox7_u6fbg%3A1680254294624&ei=VqUmZILfJemrkdUP7PyLkAk&oq=pha&gs_lcp=Cgxnd3Mtd2l6LXNlcnAQAxgAMgQIIxAnMgoIABCKBRCxAxBDMg0IABCKBRCxAxDJAxBDMggIABCABBCSAzIICAAQgAQQkgMyBwgAEIoFEEMyBwgAEIoFEEMyBwgAEIoFEEMyBwgAEIoFEEMyBwguEIoFEEM6BwgjEOoCECc6DQguEMcBENEDEOoCECc6DwgAEIoFEOoCELQCEEMYAToPCC4QigUQ6gIQtAIQQxgBOgsIABCABBCxAxCDAToICC4QgAQQsQM6CwgAEIoFELEDEIMBSgQIQRgAUABY8N0CYMzpAmgCcAF4AIABYIgBhQKSAQEzmAEAoAEBsAEUwAEB2gEGCAEQARgB&sclient=gws-wiz-serp-2",
    "sampleCount" : 1,
    "errorCount" : 0,
    "errorPct" : 0.0,
    "meanResTime" : 135.0,
    "medianResTime" : 135.0,
    "minResTime" : 135.0,
    "maxResTime" : 135.0,
    "pct1ResTime" : 135.0,
    "pct2ResTime" : 135.0,
    "pct3ResTime" : 135.0,
    "throughput" : 7.407407407407407,
    "receivedKBytesPerSec" : 6.662326388888888,
    "sentKBytesPerSec" : 7.761863425925926
  },
  "https://pharma-shop.tn/-49" : {
    "transaction" : "https://pharma-shop.tn/-49",
    "sampleCount" : 2,
    "errorCount" : 0,
    "errorPct" : 0.0,
    "meanResTime" : 61.0,
    "medianResTime" : 61.0,
    "minResTime" : 33.0,
    "maxResTime" : 89.0,
    "pct1ResTime" : 89.0,
    "pct2ResTime" : 89.0,
    "pct3ResTime" : 89.0,
    "throughput" : 0.2942907592701589,
    "receivedKBytesPerSec" : 0.8018273616833431,
    "sentKBytesPerSec" : 0.24514650161859916
  },
  "https://www.google.com/search?q=pharmashop&rlz=1C1PNJJ_frTN1050TN1050&sxsrf=APwXEdcSiZBW1PpYTEzwUR_yEox7_u6fbg%3A1680254294624&ei=VqUmZILfJemrkdUP7PyLkAk&oq=pha&gs_lcp=Cgxnd3Mtd2l6LXNlcnAQAxgAMgQIIxAnMgoIABCKBRCxAxBDMg0IABCKBRCxAxDJAxBDMggIABCABBCSAzIICAAQgAQQkgMyBwgAEIoFEEMyBwgAEIoFEEMyBwgAEIoFEEMyBwgAEIoFEEMyBwguEIoFEEM6BwgjEOoCECc6DQguEMcBENEDEOoCECc6DwgAEIoFEOoCELQCEEMYAToPCC4QigUQ6gIQtAIQQxgBOgsIABCABBCxAxCDAToICC4QgAQQsQM6CwgAEIoFELEDEIMBSgQIQRgAUABY8N0CYMzpAmgCcAF4AIABYIgBhQKSAQEzmAEAoAEBsAEUwAEB2gEGCAEQARgB&sclient=gws-wiz-serp-0" : {
    "transaction" : "https://www.google.com/search?q=pharmashop&rlz=1C1PNJJ_frTN1050TN1050&sxsrf=APwXEdcSiZBW1PpYTEzwUR_yEox7_u6fbg%3A1680254294624&ei=VqUmZILfJemrkdUP7PyLkAk&oq=pha&gs_lcp=Cgxnd3Mtd2l6LXNlcnAQAxgAMgQIIxAnMgoIABCKBRCxAxBDMg0IABCKBRCxAxDJAxBDMggIABCABBCSAzIICAAQgAQQkgMyBwgAEIoFEEMyBwgAEIoFEEMyBwgAEIoFEEMyBwgAEIoFEEMyBwguEIoFEEM6BwgjEOoCECc6DQguEMcBENEDEOoCECc6DwgAEIoFEOoCELQCEEMYAToPCC4QigUQ6gIQtAIQQxgBOgsIABCABBCxAxCDAToICC4QgAQQsQM6CwgAEIoFELEDEIMBSgQIQRgAUABY8N0CYMzpAmgCcAF4AIABYIgBhQKSAQEzmAEAoAEBsAEUwAEB2gEGCAEQARgB&sclient=gws-wiz-serp-0",
    "sampleCount" : 1,
    "errorCount" : 0,
    "errorPct" : 0.0,
    "meanResTime" : 1188.0,
    "medianResTime" : 1188.0,
    "minResTime" : 1188.0,
    "maxResTime" : 1188.0,
    "pct1ResTime" : 1188.0,
    "pct2ResTime" : 1188.0,
    "pct3ResTime" : 1188.0,
    "throughput" : 0.8417508417508417,
    "receivedKBytesPerSec" : 324.30835043139734,
    "sentKBytesPerSec" : 1.0727391098484849
  },
  "https://www.google.com/complete/search?q=pharmashop&cp=0&client=desktop-gws-wiz-on-focus-serp&xssi=t&hl=fr-TN&authuser=0&pq=pharmashop&psi=iKUmZPv1G7ypkdUP4pSpgAo.1680254346734&ofp=EAEypQEKCgoIcGFyYXNob3AKFAoScGhhcm1hc2hvcCB0dW5pc2llChMKEXBoYXJtYXNob3Agc291c3NlCg8KDXBhcmFwaGFybWFjaWUKFwoVcGhhcm1hc2hvcCBtYXF1aWxsYWdlChMKEXBoYXJtYXNob3Agb25saW5lChQKEnBoYXJtYXNob3AgY29udGFjdAoVChNwaGFybWFzaG9wIGJvbiBwbGFuEEc&dpr=1.25" : {
    "transaction" : "https://www.google.com/complete/search?q=pharmashop&cp=0&client=desktop-gws-wiz-on-focus-serp&xssi=t&hl=fr-TN&authuser=0&pq=pharmashop&psi=iKUmZPv1G7ypkdUP4pSpgAo.1680254346734&ofp=EAEypQEKCgoIcGFyYXNob3AKFAoScGhhcm1hc2hvcCB0dW5pc2llChMKEXBoYXJtYXNob3Agc291c3NlCg8KDXBhcmFwaGFybWFjaWUKFwoVcGhhcm1hc2hvcCBtYXF1aWxsYWdlChMKEXBoYXJtYXNob3Agb25saW5lChQKEnBoYXJtYXNob3AgY29udGFjdAoVChNwaGFybWFzaG9wIGJvbiBwbGFuEEc&dpr=1.25",
    "sampleCount" : 1,
    "errorCount" : 0,
    "errorPct" : 0.0,
    "meanResTime" : 85.0,
    "medianResTime" : 85.0,
    "minResTime" : 85.0,
    "maxResTime" : 85.0,
    "pct1ResTime" : 85.0,
    "pct2ResTime" : 85.0,
    "pct3ResTime" : 85.0,
    "throughput" : 11.76470588235294,
    "receivedKBytesPerSec" : 44.85294117647059,
    "sentKBytesPerSec" : 14.843749999999998
  },
  "https://www.google.com/complete/search?q=p&cp=1&client=gws-wiz-serp&xssi=t&hl=fr-TN&authuser=0&pq=google&psi=VqUmZILfJemrkdUP7PyLkAk.1680254295265&dpr=1.25" : {
    "transaction" : "https://www.google.com/complete/search?q=p&cp=1&client=gws-wiz-serp&xssi=t&hl=fr-TN&authuser=0&pq=google&psi=VqUmZILfJemrkdUP7PyLkAk.1680254295265&dpr=1.25",
    "sampleCount" : 1,
    "errorCount" : 0,
    "errorPct" : 0.0,
    "meanResTime" : 731.0,
    "medianResTime" : 731.0,
    "minResTime" : 731.0,
    "maxResTime" : 731.0,
    "pct1ResTime" : 731.0,
    "pct2ResTime" : 731.0,
    "pct3ResTime" : 731.0,
    "throughput" : 1.3679890560875512,
    "receivedKBytesPerSec" : 3.7379232216142273,
    "sentKBytesPerSec" : 1.0086247435020521
  },
  "https://pharma-shop.tn/-72" : {
    "transaction" : "https://pharma-shop.tn/-72",
    "sampleCount" : 2,
    "errorCount" : 0,
    "errorPct" : 0.0,
    "meanResTime" : 37.5,
    "medianResTime" : 37.5,
    "minResTime" : 37.0,
    "maxResTime" : 38.0,
    "pct1ResTime" : 38.0,
    "pct2ResTime" : 38.0,
    "pct3ResTime" : 38.0,
    "throughput" : 0.3092624091541673,
    "receivedKBytesPerSec" : 0.7547331645276018,
    "sentKBytesPerSec" : 0.25640994665223443
  },
  "https://pharma-shop.tn/-73" : {
    "transaction" : "https://pharma-shop.tn/-73",
    "sampleCount" : 2,
    "errorCount" : 0,
    "errorPct" : 0.0,
    "meanResTime" : 37.0,
    "medianResTime" : 37.0,
    "minResTime" : 34.0,
    "maxResTime" : 40.0,
    "pct1ResTime" : 40.0,
    "pct2ResTime" : 40.0,
    "pct3ResTime" : 40.0,
    "throughput" : 0.3088803088803089,
    "receivedKBytesPerSec" : 0.6762789575289576,
    "sentKBytesPerSec" : 0.25971283783783783
  },
  "https://pharma-shop.tn/-70" : {
    "transaction" : "https://pharma-shop.tn/-70",
    "sampleCount" : 2,
    "errorCount" : 0,
    "errorPct" : 0.0,
    "meanResTime" : 38.0,
    "medianResTime" : 38.0,
    "minResTime" : 37.0,
    "maxResTime" : 39.0,
    "pct1ResTime" : 39.0,
    "pct2ResTime" : 39.0,
    "pct3ResTime" : 39.0,
    "throughput" : 0.3089280197713933,
    "receivedKBytesPerSec" : 0.49989621949335805,
    "sentKBytesPerSec" : 0.25251245366079705
  },
  "https://pharma-shop.tn/-71" : {
    "transaction" : "https://pharma-shop.tn/-71",
    "sampleCount" : 2,
    "errorCount" : 0,
    "errorPct" : 0.0,
    "meanResTime" : 40.0,
    "medianResTime" : 40.0,
    "minResTime" : 36.0,
    "maxResTime" : 44.0,
    "pct1ResTime" : 44.0,
    "pct2ResTime" : 44.0,
    "pct3ResTime" : 44.0,
    "throughput" : 0.3090234857849196,
    "receivedKBytesPerSec" : 0.5582943834981459,
    "sentKBytesPerSec" : 0.2595314431396786
  },
  "https://pharma-shop.tn/-76" : {
    "transaction" : "https://pharma-shop.tn/-76",
    "sampleCount" : 2,
    "errorCount" : 0,
    "errorPct" : 0.0,
    "meanResTime" : 39.5,
    "medianResTime" : 39.5,
    "minResTime" : 35.0,
    "maxResTime" : 44.0,
    "pct1ResTime" : 44.0,
    "pct2ResTime" : 44.0,
    "pct3ResTime" : 44.0,
    "throughput" : 0.30907124092103233,
    "receivedKBytesPerSec" : 0.7898822631741617,
    "sentKBytesPerSec" : 0.260778859527121
  },
  "https://pharma-shop.tn/-77" : {
    "transaction" : "https://pharma-shop.tn/-77",
    "sampleCount" : 2,
    "errorCount" : 0,
    "errorPct" : 0.0,
    "meanResTime" : 41.5,
    "medianResTime" : 41.5,
    "minResTime" : 37.0,
    "maxResTime" : 46.0,
    "pct1ResTime" : 46.0,
    "pct2ResTime" : 46.0,
    "pct3ResTime" : 46.0,
    "throughput" : 0.3089280197713933,
    "receivedKBytesPerSec" : 0.5448476598702502,
    "sentKBytesPerSec" : 0.25583101637318506
  },
  "https://pharma-shop.tn/-74" : {
    "transaction" : "https://pharma-shop.tn/-74",
    "sampleCount" : 2,
    "errorCount" : 0,
    "errorPct" : 0.0,
    "meanResTime" : 37.0,
    "medianResTime" : 37.0,
    "minResTime" : 33.0,
    "maxResTime" : 41.0,
    "pct1ResTime" : 41.0,
    "pct2ResTime" : 41.0,
    "pct3ResTime" : 41.0,
    "throughput" : 0.30883261272390367,
    "receivedKBytesPerSec" : 0.7711767487646696,
    "sentKBytesPerSec" : 0.2581647621988882
  },
  "https://pharma-shop.tn/-75" : {
    "transaction" : "https://pharma-shop.tn/-75",
    "sampleCount" : 2,
    "errorCount" : 0,
    "errorPct" : 0.0,
    "meanResTime" : 43.5,
    "medianResTime" : 43.5,
    "minResTime" : 39.0,
    "maxResTime" : 48.0,
    "pct1ResTime" : 48.0,
    "pct2ResTime" : 48.0,
    "pct3ResTime" : 48.0,
    "throughput" : 0.30840400925212025,
    "receivedKBytesPerSec" : 0.5526575751734772,
    "sentKBytesPerSec" : 0.25087943330763296
  },
  "https://www.google.com/complete/search?q=pha&cp=3&client=gws-wiz-serp&xssi=t&hl=fr-TN&authuser=0&pq=google&psi=VqUmZILfJemrkdUP7PyLkAk.1680254295265&dpr=1.25" : {
    "transaction" : "https://www.google.com/complete/search?q=pha&cp=3&client=gws-wiz-serp&xssi=t&hl=fr-TN&authuser=0&pq=google&psi=VqUmZILfJemrkdUP7PyLkAk.1680254295265&dpr=1.25",
    "sampleCount" : 1,
    "errorCount" : 0,
    "errorPct" : 0.0,
    "meanResTime" : 90.0,
    "medianResTime" : 90.0,
    "minResTime" : 90.0,
    "maxResTime" : 90.0,
    "pct1ResTime" : 90.0,
    "pct2ResTime" : 90.0,
    "pct3ResTime" : 90.0,
    "throughput" : 11.11111111111111,
    "receivedKBytesPerSec" : 28.83029513888889,
    "sentKBytesPerSec" : 8.213975694444445
  },
  "https://pharma-shop.tn/-78" : {
    "transaction" : "https://pharma-shop.tn/-78",
    "sampleCount" : 2,
    "errorCount" : 0,
    "errorPct" : 0.0,
    "meanResTime" : 39.0,
    "medianResTime" : 39.0,
    "minResTime" : 35.0,
    "maxResTime" : 43.0,
    "pct1ResTime" : 43.0,
    "pct2ResTime" : 43.0,
    "pct3ResTime" : 43.0,
    "throughput" : 0.3094538140182578,
    "receivedKBytesPerSec" : 1.3039972729382638,
    "sentKBytesPerSec" : 0.2571730427046263
  },
  "https://pharma-shop.tn/-79" : {
    "transaction" : "https://pharma-shop.tn/-79",
    "sampleCount" : 2,
    "errorCount" : 0,
    "errorPct" : 0.0,
    "meanResTime" : 72.0,
    "medianResTime" : 72.0,
    "minResTime" : 32.0,
    "maxResTime" : 112.0,
    "pct1ResTime" : 112.0,
    "pct2ResTime" : 112.0,
    "pct3ResTime" : 112.0,
    "throughput" : 0.30921459492888065,
    "receivedKBytesPerSec" : 20.77762035211812,
    "sentKBytesPerSec" : 0.25727620593692024
  },
  "https://pharma-shop.tn/-109" : {
    "transaction" : "https://pharma-shop.tn/-109",
    "sampleCount" : 2,
    "errorCount" : 0,
    "errorPct" : 0.0,
    "meanResTime" : 39.0,
    "medianResTime" : 39.0,
    "minResTime" : 37.0,
    "maxResTime" : 41.0,
    "pct1ResTime" : 41.0,
    "pct2ResTime" : 41.0,
    "pct3ResTime" : 41.0,
    "throughput" : 0.3118178983473651,
    "receivedKBytesPerSec" : 0.7838078811973808,
    "sentKBytesPerSec" : 0.2594422357343312
  },
  "https://pharma-shop.tn/-108" : {
    "transaction" : "https://pharma-shop.tn/-108",
    "sampleCount" : 2,
    "errorCount" : 0,
    "errorPct" : 0.0,
    "meanResTime" : 37.0,
    "medianResTime" : 37.0,
    "minResTime" : 36.0,
    "maxResTime" : 38.0,
    "pct1ResTime" : 38.0,
    "pct2ResTime" : 38.0,
    "pct3ResTime" : 38.0,
    "throughput" : 0.31186652112895685,
    "receivedKBytesPerSec" : 0.682817129268673,
    "sentKBytesPerSec" : 0.2518687626695774
  },
  "https://pharma-shop.tn/-107" : {
    "transaction" : "https://pharma-shop.tn/-107",
    "sampleCount" : 2,
    "errorCount" : 0,
    "errorPct" : 0.0,
    "meanResTime" : 37.5,
    "medianResTime" : 37.5,
    "minResTime" : 36.0,
    "maxResTime" : 39.0,
    "pct1ResTime" : 39.0,
    "pct2ResTime" : 39.0,
    "pct3ResTime" : 39.0,
    "throughput" : 0.3114779629341224,
    "receivedKBytesPerSec" : 0.7476687821211649,
    "sentKBytesPerSec" : 0.2545967333748637
  },
  "https://pharma-shop.tn/-106" : {
    "transaction" : "https://pharma-shop.tn/-106",
    "sampleCount" : 2,
    "errorCount" : 0,
    "errorPct" : 0.0,
    "meanResTime" : 37.0,
    "medianResTime" : 37.0,
    "minResTime" : 34.0,
    "maxResTime" : 40.0,
    "pct1ResTime" : 40.0,
    "pct2ResTime" : 40.0,
    "pct3ResTime" : 40.0,
    "throughput" : 0.3109936246306951,
    "receivedKBytesPerSec" : 0.9864329031254859,
    "sentKBytesPerSec" : 0.2575415953972944
  },
  "https://pharma-shop.tn/-105" : {
    "transaction" : "https://pharma-shop.tn/-105",
    "sampleCount" : 2,
    "errorCount" : 0,
    "errorPct" : 0.0,
    "meanResTime" : 40.0,
    "medianResTime" : 40.0,
    "minResTime" : 35.0,
    "maxResTime" : 45.0,
    "pct1ResTime" : 45.0,
    "pct2ResTime" : 45.0,
    "pct3ResTime" : 45.0,
    "throughput" : 0.3108003108003108,
    "receivedKBytesPerSec" : 1.1870507964257966,
    "sentKBytesPerSec" : 0.2561674436674437
  },
  "https://pharma-shop.tn/-104" : {
    "transaction" : "https://pharma-shop.tn/-104",
    "sampleCount" : 2,
    "errorCount" : 0,
    "errorPct" : 0.0,
    "meanResTime" : 39.0,
    "medianResTime" : 39.0,
    "minResTime" : 38.0,
    "maxResTime" : 40.0,
    "pct1ResTime" : 40.0,
    "pct2ResTime" : 40.0,
    "pct3ResTime" : 40.0,
    "throughput" : 0.3116235587410408,
    "receivedKBytesPerSec" : 0.5754688960735431,
    "sentKBytesPerSec" : 0.2528898215955126
  },
  "https://pharma-shop.tn/-103" : {
    "transaction" : "https://pharma-shop.tn/-103",
    "sampleCount" : 2,
    "errorCount" : 0,
    "errorPct" : 0.0,
    "meanResTime" : 36.0,
    "medianResTime" : 36.0,
    "minResTime" : 33.0,
    "maxResTime" : 39.0,
    "pct1ResTime" : 39.0,
    "pct2ResTime" : 39.0,
    "pct3ResTime" : 39.0,
    "throughput" : 0.3117692907248636,
    "receivedKBytesPerSec" : 0.7188352494154325,
    "sentKBytesPerSec" : 0.2557482462977397
  },
  "https://pharma-shop.tn/-102" : {
    "transaction" : "https://pharma-shop.tn/-102",
    "sampleCount" : 2,
    "errorCount" : 0,
    "errorPct" : 0.0,
    "meanResTime" : 37.5,
    "medianResTime" : 37.5,
    "minResTime" : 37.0,
    "maxResTime" : 38.0,
    "pct1ResTime" : 38.0,
    "pct2ResTime" : 38.0,
    "pct3ResTime" : 38.0,
    "throughput" : 0.3117206982543641,
    "receivedKBytesPerSec" : 0.5869116271820448,
    "sentKBytesPerSec" : 0.2590569474750623
  },
  "https://pharma-shop.tn/-101" : {
    "transaction" : "https://pharma-shop.tn/-101",
    "sampleCount" : 2,
    "errorCount" : 0,
    "errorPct" : 0.0,
    "meanResTime" : 39.0,
    "medianResTime" : 39.0,
    "minResTime" : 35.0,
    "maxResTime" : 43.0,
    "pct1ResTime" : 43.0,
    "pct2ResTime" : 43.0,
    "pct3ResTime" : 43.0,
    "throughput" : 0.31133250311332505,
    "receivedKBytesPerSec" : 0.7309016967621419,
    "sentKBytesPerSec" : 0.25569397960772106
  },
  "https://pharma-shop.tn/-100" : {
    "transaction" : "https://pharma-shop.tn/-100",
    "sampleCount" : 2,
    "errorCount" : 0,
    "errorPct" : 0.0,
    "meanResTime" : 35.5,
    "medianResTime" : 35.5,
    "minResTime" : 35.0,
    "maxResTime" : 36.0,
    "pct1ResTime" : 36.0,
    "pct2ResTime" : 36.0,
    "pct3ResTime" : 36.0,
    "throughput" : 0.31094527363184077,
    "receivedKBytesPerSec" : 0.6224978622512437,
    "sentKBytesPerSec" : 0.2593234996890547
  },
  "https://www.google.com/complete/search?q=ph&cp=2&client=gws-wiz-serp&xssi=t&hl=fr-TN&authuser=0&pq=google&psi=VqUmZILfJemrkdUP7PyLkAk.1680254295265&dpr=1.25" : {
    "transaction" : "https://www.google.com/complete/search?q=ph&cp=2&client=gws-wiz-serp&xssi=t&hl=fr-TN&authuser=0&pq=google&psi=VqUmZILfJemrkdUP7PyLkAk.1680254295265&dpr=1.25",
    "sampleCount" : 1,
    "errorCount" : 0,
    "errorPct" : 0.0,
    "meanResTime" : 96.0,
    "medianResTime" : 96.0,
    "minResTime" : 96.0,
    "maxResTime" : 96.0,
    "pct1ResTime" : 96.0,
    "pct2ResTime" : 96.0,
    "pct3ResTime" : 96.0,
    "throughput" : 10.416666666666666,
    "receivedKBytesPerSec" : 28.798421223958332,
    "sentKBytesPerSec" : 7.6904296875
  },
  "https://pharma-shop.tn/-61" : {
    "transaction" : "https://pharma-shop.tn/-61",
    "sampleCount" : 2,
    "errorCount" : 0,
    "errorPct" : 0.0,
    "meanResTime" : 38.0,
    "medianResTime" : 38.0,
    "minResTime" : 34.0,
    "maxResTime" : 42.0,
    "pct1ResTime" : 42.0,
    "pct2ResTime" : 42.0,
    "pct3ResTime" : 42.0,
    "throughput" : 0.30821390044691016,
    "receivedKBytesPerSec" : 1.336998189243335,
    "sentKBytesPerSec" : 0.26186141932501156
  },
  "https://pharma-shop.tn/-62" : {
    "transaction" : "https://pharma-shop.tn/-62",
    "sampleCount" : 2,
    "errorCount" : 0,
    "errorPct" : 0.0,
    "meanResTime" : 39.5,
    "medianResTime" : 39.5,
    "minResTime" : 35.0,
    "maxResTime" : 44.0,
    "pct1ResTime" : 44.0,
    "pct2ResTime" : 44.0,
    "pct3ResTime" : 44.0,
    "throughput" : 0.3083089255433945,
    "receivedKBytesPerSec" : 1.2476876830584245,
    "sentKBytesPerSec" : 0.2619421535378449
  },
  "https://pharma-shop.tn/-60" : {
    "transaction" : "https://pharma-shop.tn/-60",
    "sampleCount" : 2,
    "errorCount" : 0,
    "errorPct" : 0.0,
    "meanResTime" : 44.5,
    "medianResTime" : 44.5,
    "minResTime" : 37.0,
    "maxResTime" : 52.0,
    "pct1ResTime" : 52.0,
    "pct2ResTime" : 52.0,
    "pct3ResTime" : 52.0,
    "throughput" : 0.3079765937788728,
    "receivedKBytesPerSec" : 1.3251414767477672,
    "sentKBytesPerSec" : 0.2544415999384047
  },
  "https://pharma-shop.tn/-65" : {
    "transaction" : "https://pharma-shop.tn/-65",
    "sampleCount" : 2,
    "errorCount" : 0,
    "errorPct" : 0.0,
    "meanResTime" : 47.5,
    "medianResTime" : 47.5,
    "minResTime" : 41.0,
    "maxResTime" : 54.0,
    "pct1ResTime" : 54.0,
    "pct2ResTime" : 54.0,
    "pct3ResTime" : 54.0,
    "throughput" : 0.30807147258163897,
    "receivedKBytesPerSec" : 0.932638247073321,
    "sentKBytesPerSec" : 0.25993530499075784
  },
  "https://pharma-shop.tn/-66" : {
    "transaction" : "https://pharma-shop.tn/-66",
    "sampleCount" : 2,
    "errorCount" : 0,
    "errorPct" : 0.0,
    "meanResTime" : 43.5,
    "medianResTime" : 43.5,
    "minResTime" : 36.0,
    "maxResTime" : 51.0,
    "pct1ResTime" : 51.0,
    "pct2ResTime" : 51.0,
    "pct3ResTime" : 51.0,
    "throughput" : 0.3086896125945362,
    "receivedKBytesPerSec" : 1.7868727330606575,
    "sentKBytesPerSec" : 0.26226558882543605
  },
  "https://pharma-shop.tn/-63" : {
    "transaction" : "https://pharma-shop.tn/-63",
    "sampleCount" : 2,
    "errorCount" : 0,
    "errorPct" : 0.0,
    "meanResTime" : 36.5,
    "medianResTime" : 36.5,
    "minResTime" : 34.0,
    "maxResTime" : 39.0,
    "pct1ResTime" : 39.0,
    "pct2ResTime" : 39.0,
    "pct3ResTime" : 39.0,
    "throughput" : 0.30816640986132515,
    "receivedKBytesPerSec" : 0.6864527157164869,
    "sentKBytesPerSec" : 0.26422862095531585
  },
  "https://pharma-shop.tn/-64" : {
    "transaction" : "https://pharma-shop.tn/-64",
    "sampleCount" : 2,
    "errorCount" : 0,
    "errorPct" : 0.0,
    "meanResTime" : 43.5,
    "medianResTime" : 43.5,
    "minResTime" : 35.0,
    "maxResTime" : 52.0,
    "pct1ResTime" : 52.0,
    "pct2ResTime" : 52.0,
    "pct3ResTime" : 52.0,
    "throughput" : 0.30821390044691016,
    "receivedKBytesPerSec" : 1.431208102172908,
    "sentKBytesPerSec" : 0.2573465672676838
  },
  "https://pharma-shop.tn/-69" : {
    "transaction" : "https://pharma-shop.tn/-69",
    "sampleCount" : 2,
    "errorCount" : 0,
    "errorPct" : 0.0,
    "meanResTime" : 36.0,
    "medianResTime" : 36.0,
    "minResTime" : 35.0,
    "maxResTime" : 37.0,
    "pct1ResTime" : 37.0,
    "pct2ResTime" : 37.0,
    "pct3ResTime" : 37.0,
    "throughput" : 0.308546744831842,
    "receivedKBytesPerSec" : 0.5095239702252391,
    "sentKBytesPerSec" : 0.25672053378586857
  },
  "https://pharma-shop.tn/-67" : {
    "transaction" : "https://pharma-shop.tn/-67",
    "sampleCount" : 2,
    "errorCount" : 0,
    "errorPct" : 0.0,
    "meanResTime" : 48.5,
    "medianResTime" : 48.5,
    "minResTime" : 46.0,
    "maxResTime" : 51.0,
    "pct1ResTime" : 51.0,
    "pct2ResTime" : 51.0,
    "pct3ResTime" : 51.0,
    "throughput" : 0.30807147258163897,
    "receivedKBytesPerSec" : 0.9377527148798521,
    "sentKBytesPerSec" : 0.25331658194701173
  },
  "https://pharma-shop.tn/-68" : {
    "transaction" : "https://pharma-shop.tn/-68",
    "sampleCount" : 2,
    "errorCount" : 0,
    "errorPct" : 0.0,
    "meanResTime" : 37.5,
    "medianResTime" : 37.5,
    "minResTime" : 36.0,
    "maxResTime" : 39.0,
    "pct1ResTime" : 39.0,
    "pct2ResTime" : 39.0,
    "pct3ResTime" : 39.0,
    "throughput" : 0.30849915162733305,
    "receivedKBytesPerSec" : 0.661284802560543,
    "sentKBytesPerSec" : 0.2569822034551905
  },
  "https://pharma-shop.tn/module/ets_sociallogin/oauth" : {
    "transaction" : "https://pharma-shop.tn/module/ets_sociallogin/oauth",
    "sampleCount" : 1,
    "errorCount" : 0,
    "errorPct" : 0.0,
    "meanResTime" : 475.0,
    "medianResTime" : 475.0,
    "minResTime" : 475.0,
    "maxResTime" : 475.0,
    "pct1ResTime" : 475.0,
    "pct2ResTime" : 475.0,
    "pct3ResTime" : 475.0,
    "throughput" : 2.1052631578947367,
    "receivedKBytesPerSec" : 3.1681743421052633,
    "sentKBytesPerSec" : 1.274671052631579
  },
  "https://pharma-shop.tn/-119" : {
    "transaction" : "https://pharma-shop.tn/-119",
    "sampleCount" : 2,
    "errorCount" : 0,
    "errorPct" : 0.0,
    "meanResTime" : 189.5,
    "medianResTime" : 189.5,
    "minResTime" : 35.0,
    "maxResTime" : 344.0,
    "pct1ResTime" : 344.0,
    "pct2ResTime" : 344.0,
    "pct3ResTime" : 344.0,
    "throughput" : 0.31446540880503143,
    "receivedKBytesPerSec" : 138.5227803164308,
    "sentKBytesPerSec" : 0.255503144654088
  },
  "https://pharma-shop.tn/-118" : {
    "transaction" : "https://pharma-shop.tn/-118",
    "sampleCount" : 2,
    "errorCount" : 0,
    "errorPct" : 0.0,
    "meanResTime" : 50.5,
    "medianResTime" : 50.5,
    "minResTime" : 32.0,
    "maxResTime" : 69.0,
    "pct1ResTime" : 69.0,
    "pct2ResTime" : 69.0,
    "pct3ResTime" : 69.0,
    "throughput" : 0.3131850923896023,
    "receivedKBytesPerSec" : 0.4109025113529596,
    "sentKBytesPerSec" : 0.26287362002818665
  },
  "Total" : {
    "transaction" : "Total",
    "sampleCount" : 263,
    "errorCount" : 1,
    "errorPct" : 0.38022813,
    "meanResTime" : 124.50570342205322,
    "medianResTime" : 41.0,
    "minResTime" : 22.0,
    "maxResTime" : 3396.0,
    "pct1ResTime" : 230.99999999999997,
    "pct2ResTime" : 470.39999999999964,
    "pct3ResTime" : 1639.9200000000087,
    "throughput" : 21.455376080926744,
    "receivedKBytesPerSec" : 1445.924424992862,
    "sentKBytesPerSec" : 33.61874961759668
  },
  "https://pharma-shop.tn/-117" : {
    "transaction" : "https://pharma-shop.tn/-117",
    "sampleCount" : 2,
    "errorCount" : 0,
    "errorPct" : 0.0,
    "meanResTime" : 57.5,
    "medianResTime" : 57.5,
    "minResTime" : 33.0,
    "maxResTime" : 82.0,
    "pct1ResTime" : 82.0,
    "pct2ResTime" : 82.0,
    "pct3ResTime" : 82.0,
    "throughput" : 0.3132832080200501,
    "receivedKBytesPerSec" : 1.3684724506578947,
    "sentKBytesPerSec" : 0.24597626879699247
  },
  "https://pharma-shop.tn/-116" : {
    "transaction" : "https://pharma-shop.tn/-116",
    "sampleCount" : 2,
    "errorCount" : 0,
    "errorPct" : 0.0,
    "meanResTime" : 43.0,
    "medianResTime" : 43.0,
    "minResTime" : 35.0,
    "maxResTime" : 51.0,
    "pct1ResTime" : 51.0,
    "pct2ResTime" : 51.0,
    "pct3ResTime" : 51.0,
    "throughput" : 0.31367628607277287,
    "receivedKBytesPerSec" : 0.573439460476788,
    "sentKBytesPerSec" : 0.24475327399623586
  },
  "https://pharma-shop.tn/-115" : {
    "transaction" : "https://pharma-shop.tn/-115",
    "sampleCount" : 2,
    "errorCount" : 0,
    "errorPct" : 0.0,
    "meanResTime" : 58.5,
    "medianResTime" : 58.5,
    "minResTime" : 36.0,
    "maxResTime" : 81.0,
    "pct1ResTime" : 81.0,
    "pct2ResTime" : 81.0,
    "pct3ResTime" : 81.0,
    "throughput" : 0.3121098626716604,
    "receivedKBytesPerSec" : 1.224055867665418,
    "sentKBytesPerSec" : 0.2435310354244694
  },
  "https://pharma-shop.tn/-114" : {
    "transaction" : "https://pharma-shop.tn/-114",
    "sampleCount" : 2,
    "errorCount" : 0,
    "errorPct" : 0.0,
    "meanResTime" : 65.5,
    "medianResTime" : 65.5,
    "minResTime" : 33.0,
    "maxResTime" : 98.0,
    "pct1ResTime" : 98.0,
    "pct2ResTime" : 98.0,
    "pct3ResTime" : 98.0,
    "throughput" : 0.3121098626716604,
    "receivedKBytesPerSec" : 2.2698067844881398,
    "sentKBytesPerSec" : 0.2435310354244694
  },
  "https://pharma-shop.tn/-113" : {
    "transaction" : "https://pharma-shop.tn/-113",
    "sampleCount" : 2,
    "errorCount" : 0,
    "errorPct" : 0.0,
    "meanResTime" : 46.5,
    "medianResTime" : 46.5,
    "minResTime" : 35.0,
    "maxResTime" : 58.0,
    "pct1ResTime" : 58.0,
    "pct2ResTime" : 58.0,
    "pct3ResTime" : 58.0,
    "throughput" : 0.31167212092878294,
    "receivedKBytesPerSec" : 0.7578745909303413,
    "sentKBytesPerSec" : 0.24318947717001715
  },
  "https://pharma-shop.tn/-112" : {
    "transaction" : "https://pharma-shop.tn/-112",
    "sampleCount" : 2,
    "errorCount" : 0,
    "errorPct" : 0.0,
    "meanResTime" : 50.0,
    "medianResTime" : 50.0,
    "minResTime" : 36.0,
    "maxResTime" : 64.0,
    "pct1ResTime" : 64.0,
    "pct2ResTime" : 64.0,
    "pct3ResTime" : 64.0,
    "throughput" : 0.31123560535325245,
    "receivedKBytesPerSec" : 1.7549554544039838,
    "sentKBytesPerSec" : 0.25956563180827885
  },
  "https://pharma-shop.tn/-111" : {
    "transaction" : "https://pharma-shop.tn/-111",
    "sampleCount" : 2,
    "errorCount" : 0,
    "errorPct" : 0.0,
    "meanResTime" : 53.0,
    "medianResTime" : 53.0,
    "minResTime" : 33.0,
    "maxResTime" : 73.0,
    "pct1ResTime" : 73.0,
    "pct2ResTime" : 73.0,
    "pct3ResTime" : 73.0,
    "throughput" : 0.31133250311332505,
    "receivedKBytesPerSec" : 1.733763280277086,
    "sentKBytesPerSec" : 0.2596464430261519
  },
  "https://pharma-shop.tn/-110" : {
    "transaction" : "https://pharma-shop.tn/-110",
    "sampleCount" : 2,
    "errorCount" : 0,
    "errorPct" : 0.0,
    "meanResTime" : 74.5,
    "medianResTime" : 74.5,
    "minResTime" : 35.0,
    "maxResTime" : 114.0,
    "pct1ResTime" : 114.0,
    "pct2ResTime" : 114.0,
    "pct3ResTime" : 114.0,
    "throughput" : 0.31186652112895685,
    "receivedKBytesPerSec" : 12.577753440277561,
    "sentKBytesPerSec" : 0.25856901995945736
  }
}